{"kind": "Listing", "data": {"modhash": "", "children": [{"kind": "t3", "data": {"contest_mode": false, "banned_by": null, "domain": "self.emojipasta", "subreddit": "emojipasta", "selftext_html": "&lt;!-- SC_OFF --&gt;&lt;div class=\"md\"&gt;&lt;p&gt;Wait \u270b\u270bwait \u270b\u270bwait \ud83d\udc4b\u270b guys stop \u203c\ufe0f\u270b\u270bfor \u270c1 sec... Pls\ud83d\udc47\ud83d\udc46\ud83d\udc48 ... If the world is billions\ud83d\udc48\ud83d\udc48\ud83d\udc46\ud83d\udc46 of years old..... then why are we in year 2015\ud83d\ude15\ud83d\ude11\ud83d\ude11???&lt;/p&gt;\n&lt;/div&gt;&lt;!-- SC_ON --&gt;", "selftext": "Wait \u270b\u270bwait \u270b\u270bwait \ud83d\udc4b\u270b guys stop \u203c\ufe0f\u270b\u270bfor \u270c1 sec... Pls\ud83d\udc47\ud83d\udc46\ud83d\udc48 ... If the world is billions\ud83d\udc48\ud83d\udc48\ud83d\udc46\ud83d\udc46 of years old..... then why are we in year 2015\ud83d\ude15\ud83d\ude11\ud83d\ude11???", "likes": null, "suggested_sort": "confidence", "user_reports": [], "secure_media": null, "saved": false, "id": "3l089g", "gilded": 0, "secure_media_embed": {}, "clicked": false, "report_reasons": null, "author": "TheGrimeySavage", "media": null, "name": "t3_3l089g", "score": 33, "approved_by": null, "over_18": false, "removal_reason": null, "hidden": false, "thumbnail": "", "subreddit_id": "t5_39n7p", "edited": false, "link_flair_css_class": null, "author_flair_css_class": null, "downs": 0, "mod_reports": [], "archived": true, "media_embed": {}, "is_self": true, "hide_score": false, "spoiler": false, "permalink": "/r/emojipasta/comments/3l089g/if_the_earth_is_billions_of_years_old_why_are_we/", "locked": false, "stickied": false, "created": 1442322176.0, "url": "https://www.reddit.com/r/emojipasta/comments/3l089g/if_the_earth_is_billions_of_years_old_why_are_we/", "author_flair_text": null, "quarantine": false, "title": "If the earth is billions of years old why are we in year 2015?", "created_utc": 1442293376.0, "link_flair_text": null, "distinguished": null, "num_comments": 8, "visited": false, "num_reports": null, "ups": 33}}, {"kind": "t3", "data": {"contest_mode": false, "banned_by": null, "domain": "self.emojipasta", "subreddit": "emojipasta", "selftext_html": "&lt;!-- SC_OFF --&gt;&lt;div class=\"md\"&gt;&lt;p&gt;\ud83d\udd2f\ud83d\udd2f\ud83d\udd2f\ud83d\udd2f\ud83d\udd2f\ud83d\udd2fspare change spaRe change\ud83d\udd2f thats \u2714 some SPARE\ud83d\udd2f\ud83d\udd2fchange right\ud83d\udd2fth \ud83d\udd2f ere right\u2714there \u2714\u2714if i do \u01bda\u04af so my sel\uff46 i say so thats what im talking about right there right there (chorus: \u02b3\u1da6\u1d4d\u02b0\u1d57 \u1d57\u02b0\u1d49\u02b3\u1d49) mMMMM\u13b7\u041c\ud83d\udcb3 \u041dO0\u041e\u0b20\uff2fOO\uff2fO\u041e\u0b20\u0b20Oooo\u1d52\u1d52\u1d52\u1d52\u1d52\u1d52\u1d52\u1d52\u1d52ly TorAh\ud83d\udd2f\ud83d\udd2f\ud83d\udd2f \ud83d\udcb3 \ud83d\udd2f \ud83d\udd2f\ud83d\udd2fspare change&lt;/p&gt;\n\n&lt;p&gt;&lt;a href=\"https://www.reddit.com/r/copypasta/comments/3kcpt5/good_shit_jewish_style/?ref=share&amp;amp;ref_source=link\"&gt;source&lt;/a&gt;&lt;/p&gt;\n&lt;/div&gt;&lt;!-- SC_ON --&gt;", "selftext": "\ud83d\udd2f\ud83d\udd2f\ud83d\udd2f\ud83d\udd2f\ud83d\udd2f\ud83d\udd2fspare change spaRe change\ud83d\udd2f thats \u2714 some SPARE\ud83d\udd2f\ud83d\udd2fchange right\ud83d\udd2fth \ud83d\udd2f ere right\u2714there \u2714\u2714if i do \u01bda\u04af so my sel\uff46 i say so thats what im talking about right there right there (chorus: \u02b3\u1da6\u1d4d\u02b0\u1d57 \u1d57\u02b0\u1d49\u02b3\u1d49) mMMMM\u13b7\u041c\ud83d\udcb3 \u041dO0\u041e\u0b20\uff2fOO\uff2fO\u041e\u0b20\u0b20Oooo\u1d52\u1d52\u1d52\u1d52\u1d52\u1d52\u1d52\u1d52\u1d52ly TorAh\ud83d\udd2f\ud83d\udd2f\ud83d\udd2f \ud83d\udcb3 \ud83d\udd2f \ud83d\udd2f\ud83d\udd2fspare change\n\n\n[source](https://www.reddit.com/r/copypasta/comments/3kcpt5/good_shit_jewish_style/?ref=share&amp;ref_source=link)", "likes": null, "suggested_sort": "confidence", "user_reports": [], "secure_media": null, "saved": false, "id": "3khkci", "gilded": 0, "secure_media_embed": {}, "clicked": false, "report_reasons": null, "author": "skech1080", "media": null, "name": "t3_3khkci", "score": 36, "approved_by": null, "over_18": false, "removal_reason": null, "hidden": false, "thumbnail": "", "subreddit_id": "t5_39n7p", "edited": false, "link_flair_css_class": null, "author_flair_css_class": null, "downs": 0, "mod_reports": [], "archived": true, "media_embed": {}, "is_self": true, "hide_score": false, "spoiler": false, "permalink": "/r/emojipasta/comments/3khkci/spare_change_spare_change_thats_some_sparechange/", "locked": false, "stickied": false, "created": 1441965040.0, "url": "https://www.reddit.com/r/emojipasta/comments/3khkci/spare_change_spare_change_thats_some_sparechange/", "author_flair_text": null, "quarantine": false, "title": "\ud83d\udd2f\ud83d\udd2f\ud83d\udd2f\ud83d\udd2f\ud83d\udd2f\ud83d\udd2fspare change spaRe change\ud83d\udd2f thats \u2714 some SPARE\ud83d\udd2f\ud83d\udd2fchange right\ud83d\udd2fth \ud83d\udd2f ere right\u2714there \u2714\u2714if i do \u01bda\u04af so my sel\uff46 i say so thats what im talking about right there right there (chorus: \u02b3\u1da6\u1d4d\u02b0\u1d57 \u1d57\u02b0\u1d49\u02b3\u1d49) mMMMM\u13b7\u041c\ud83d\udcb3 \u041dO0\u041e\u0b20\uff2fOO\uff2fO\u041e\u0b20\u0b20Oooo\u1d52\u1d52\u1d52\u1d52\u1d52\u1d52\u1d52\u1d52\u1d52ly TorAh\ud83d\udd2f\ud83d\udd2f\ud83d\udd2f \ud83d\udcb3 \ud83d\udd2f \ud83d\udd2f\ud83d\udd2fspare change", "created_utc": 1441936240.0, "link_flair_text": null, "distinguished": null, "num_comments": 5, "visited": false, "num_reports": null, "ups": 36}}, {"kind": "t3", "data": {"contest_mode": false, "banned_by": null, "domain": "self.emojipasta", "subreddit": "emojipasta", "selftext_html": "&lt;!-- SC_OFF --&gt;&lt;div class=\"md\"&gt;&lt;p&gt;\ud83d\udca6 Sex \ud83d\udca6\ud83d\udc4c\ud83d\udc48 or at least \ud83d\ude29\ud83d\ude25 romantic \ud83d\udc44\ud83c\udf51 interaction \ud83c\udf46 with \ud83d\ude48\ud83d\udc67 females \ud83d\udc91 is a \u270c basic \u270c necessity \ud83d\udc4f, like \ud83c\udf5d food \ud83c\udf55 and \ud83d\udca7water \ud83d\udc33. A \ud83d\udc68 man \ud83d\udcaa deprived \ud83d\udc83\ud83d\udc83 of women \ud83d\udc71\ud83d\udc78 \u274c won&amp;#39;t \u274c necessarily die \ud83d\udc80\ud83d\udc40, but he will \ud83d\udc45 over \u231a\u23f0 time \u231a\u23f0\ud83d\udd1c go \u231b insane\ud83d\udca2\ud83d\udcab.&lt;/p&gt;\n\n&lt;p&gt;When people \ud83d\udc65 criticize \ud83d\udc79 us \ud83d\udeb5 for being \ud83d\udc85 &amp;quot;entitled&amp;quot; \ud83d\udc7c, they \ud83d\udc7a are saying \ud83d\udcac that we don&amp;#39;t \ud83d\ude45\ud83d\ude4d\u2714 deserve \u2714 to be with \ud83d\udc6b women \ud83d\udc6a. They \ud83d\udc49 are saying \ud83d\udcac we deserve \ud83d\udeaa to be alone \ud83d\udd15\ud83d\ude2d\ud83d\udd2b. They \ud83d\ude1e are saying \ud83d\udcac it&amp;#39;s \ud83d\udc50 better\ud83d\udc4f for us\ud83d\udc42 to go \ud83d\udca5 insane \ud83d\udca5\u303d than for \ud83d\udc7f women \ud83d\udc7f to be \ud83d\udca3 inconvenienced \u23f3 with \ud83d\ude14\ud83d\ude16 interacting \ud83d\udcf2 with \ud83d\udc1a us \ud83d\udcad.&lt;/p&gt;\n&lt;/div&gt;&lt;!-- SC_ON --&gt;", "selftext": "\ud83d\udca6 Sex \ud83d\udca6\ud83d\udc4c\ud83d\udc48 or at least \ud83d\ude29\ud83d\ude25 romantic \ud83d\udc44\ud83c\udf51 interaction \ud83c\udf46 with \ud83d\ude48\ud83d\udc67 females \ud83d\udc91 is a \u270c basic \u270c necessity \ud83d\udc4f, like \ud83c\udf5d food \ud83c\udf55 and \ud83d\udca7water \ud83d\udc33. A \ud83d\udc68 man \ud83d\udcaa deprived \ud83d\udc83\ud83d\udc83 of women \ud83d\udc71\ud83d\udc78 \u274c won't \u274c necessarily die \ud83d\udc80\ud83d\udc40, but he will \ud83d\udc45 over \u231a\u23f0 time \u231a\u23f0\ud83d\udd1c go \u231b insane\ud83d\udca2\ud83d\udcab.\n\nWhen people \ud83d\udc65 criticize \ud83d\udc79 us \ud83d\udeb5 for being \ud83d\udc85 \"entitled\" \ud83d\udc7c, they \ud83d\udc7a are saying \ud83d\udcac that we don't \ud83d\ude45\ud83d\ude4d\u2714 deserve \u2714 to be with \ud83d\udc6b women \ud83d\udc6a. They \ud83d\udc49 are saying \ud83d\udcac we deserve \ud83d\udeaa to be alone \ud83d\udd15\ud83d\ude2d\ud83d\udd2b. They \ud83d\ude1e are saying \ud83d\udcac it's \ud83d\udc50 better\ud83d\udc4f for us\ud83d\udc42 to go \ud83d\udca5 insane \ud83d\udca5\u303d than for \ud83d\udc7f women \ud83d\udc7f to be \ud83d\udca3 inconvenienced \u23f3 with \ud83d\ude14\ud83d\ude16 interacting \ud83d\udcf2 with \ud83d\udc1a us \ud83d\udcad.", "likes": null, "suggested_sort": "confidence", "user_reports": [], "secure_media": null, "saved": false, "id": "5hncpg", "gilded": 0, "secure_media_embed": {}, "clicked": false, "report_reasons": null, "author": "aly5321", "media": null, "name": "t3_5hncpg", "score": 32, "approved_by": null, "over_18": false, "removal_reason": null, "hidden": false, "thumbnail": "", "subreddit_id": "t5_39n7p", "edited": false, "link_flair_css_class": null, "author_flair_css_class": null, "downs": 0, "mod_reports": [], "archived": false, "media_embed": {}, "is_self": true, "hide_score": false, "spoiler": false, "permalink": "/r/emojipasta/comments/5hncpg/sex_or_at_least_romantic_interaction_with_females/", "locked": false, "stickied": false, "created": 1481445033.0, "url": "https://www.reddit.com/r/emojipasta/comments/5hncpg/sex_or_at_least_romantic_interaction_with_females/", "author_flair_text": null, "quarantine": false, "title": "\ud83d\udca6 Sex \ud83d\udca6\ud83d\udc4c\ud83d\udc48 or at least \ud83d\ude29\ud83d\ude25 romantic \ud83d\udc44\ud83c\udf51 interaction \ud83c\udf46 with \ud83d\ude48\ud83d\udc67 females \ud83d\udc91 is a \u270c basic \u270c necessity \ud83d\udc4f, like \ud83c\udf5d food \ud83c\udf55 and \ud83d\udca7water \ud83d\udc33.", "created_utc": 1481416233.0, "link_flair_text": null, "distinguished": null, "num_comments": 7, "visited": false, "num_reports": null, "ups": 32}}, {"kind": "t3", "data": {"contest_mode": false, "banned_by": null, "domain": "self.emojipasta", "subreddit": "emojipasta", "selftext_html": "&lt;!-- SC_OFF --&gt;&lt;div class=\"md\"&gt;&lt;p&gt;\ud83d\udc3e\ud83d\udc36\ud83d\udc3e\ud83d\udc36\ud83d\udc3e\ud83d\udc36\ud83d\udc3e\ud83d\udc36\ud83d\udc3e\ud83d\udc36 good boy go\u0c66\u0501 boy\ud83d\udc3e thats \u270b a good\ud83d\udc3e\ud83d\udc3eboy right\ud83d\udc3e\ud83d\udc3ethere\ud83d\udc3e\ud83d\udc3e\ud83d\udc3e come to\u270bmommy for pets\u270b\u270bif i do \u01bda\u04af so my self \ud83d\udcaf i say so \ud83d\udcafwhos a good boy whos a good boy (answer: \u02b8\u1d52\u1d58 \u1d43\u02b3\u1d49 \u02b8\u1d49\u02e2\u02b0 \u02b8\u1d52\u1d58 \u1d43\u02b3\u1d49) mMMMM\u13b7\u041c\ud83d\udcaf \ud83d\udc3e\ud83d\udc3e \ud83d\udc3e\u041dO0\u041e\u0b20OOOOO\u041e\u0b20\u0b20Oooo\u1d52\u1d52\u1d52\u1d52\u1d52\u1d52\u1d52\u1d52\u1d52\ud83d\udc3e \ud83d\udc3e\ud83d\udc3e \ud83d\udc3e \ud83d\udcaf \ud83d\udc3e \ud83d\udc36 \ud83d\udc36 \ud83d\udc36 \ud83d\udc3e\ud83d\udc3eGood dog *pets the dog*&lt;/p&gt;\n&lt;/div&gt;&lt;!-- SC_ON --&gt;", "selftext": "\ud83d\udc3e\ud83d\udc36\ud83d\udc3e\ud83d\udc36\ud83d\udc3e\ud83d\udc36\ud83d\udc3e\ud83d\udc36\ud83d\udc3e\ud83d\udc36 good boy go\u0c66\u0501 boy\ud83d\udc3e thats \u270b a good\ud83d\udc3e\ud83d\udc3eboy right\ud83d\udc3e\ud83d\udc3ethere\ud83d\udc3e\ud83d\udc3e\ud83d\udc3e come to\u270bmommy for pets\u270b\u270bif i do \u01bda\u04af so my self \ud83d\udcaf i say so \ud83d\udcafwhos a good boy whos a good boy (answer: \u02b8\u1d52\u1d58 \u1d43\u02b3\u1d49 \u02b8\u1d49\u02e2\u02b0 \u02b8\u1d52\u1d58 \u1d43\u02b3\u1d49) mMMMM\u13b7\u041c\ud83d\udcaf \ud83d\udc3e\ud83d\udc3e \ud83d\udc3e\u041dO0\u041e\u0b20OOOOO\u041e\u0b20\u0b20Oooo\u1d52\u1d52\u1d52\u1d52\u1d52\u1d52\u1d52\u1d52\u1d52\ud83d\udc3e \ud83d\udc3e\ud83d\udc3e \ud83d\udc3e \ud83d\udcaf \ud83d\udc3e \ud83d\udc36 \ud83d\udc36 \ud83d\udc36 \ud83d\udc3e\ud83d\udc3eGood dog \\*pets the dog\\*", "likes": null, "suggested_sort": "confidence", "user_reports": [], "secure_media": null, "saved": false, "id": "5gsd65", "gilded": 0, "secure_media_embed": {}, "clicked": false, "report_reasons": null, "author": "pupper4supper", "media": null, "name": "t3_5gsd65", "score": 32, "approved_by": null, "over_18": false, "removal_reason": null, "hidden": false, "thumbnail": "", "subreddit_id": "t5_39n7p", "edited": false, "link_flair_css_class": null, "author_flair_css_class": null, "downs": 0, "mod_reports": [], "archived": false, "media_embed": {}, "is_self": true, "hide_score": false, "spoiler": false, "permalink": "/r/emojipasta/comments/5gsd65/good_boy_go\u0c66\u0501_boy_thats_a_goodboy/", "locked": false, "stickied": false, "created": 1481052648.0, "url": "https://www.reddit.com/r/emojipasta/comments/5gsd65/good_boy_go\u0c66\u0501_boy_thats_a_goodboy/", "author_flair_text": null, "quarantine": false, "title": "\ud83d\udc3e\ud83d\udc36\ud83d\udc3e\ud83d\udc36\ud83d\udc3e\ud83d\udc36\ud83d\udc3e\ud83d\udc36\ud83d\udc3e\ud83d\udc36 good boy go\u0c66\u0501 boy\ud83d\udc3e thats \u270b a good\ud83d\udc3e\ud83d\udc3eboy", "created_utc": 1481023848.0, "link_flair_text": null, "distinguished": null, "num_comments": 3, "visited": false, "num_reports": null, "ups": 32}}, {"kind": "t3", "data": {"contest_mode": false, "banned_by": null, "domain": "self.emojipasta", "subreddit": "emojipasta", "selftext_html": "&lt;!-- SC_OFF --&gt;&lt;div class=\"md\"&gt;&lt;p&gt;\ud83d\udcaf When we trend \ud83d\udcaf&lt;/p&gt;\n\n&lt;p&gt;\ud83d\udc68\ud83c\udffd Daddy makes me bend \ud83d\udd29&lt;/p&gt;\n\n&lt;p&gt;\ud83d\ude4c\ud83c\udffd Over to be  \ud83d\udc1d&lt;/p&gt;\n\n&lt;p&gt;\ud83d\udc49\ud83c\udffd A bent over me \ud83d\udc78\ud83c\udffd&lt;/p&gt;\n\n&lt;p&gt;\ud83d\udca6 then his cummies he will send \ud83d\udca9&lt;/p&gt;\n&lt;/div&gt;&lt;!-- SC_ON --&gt;", "selftext": "\ud83d\udcaf When we trend \ud83d\udcaf\n\n\n\ud83d\udc68\ud83c\udffd Daddy makes me bend \ud83d\udd29\n\n\n\ud83d\ude4c\ud83c\udffd Over to be  \ud83d\udc1d\n\n\n\ud83d\udc49\ud83c\udffd A bent over me \ud83d\udc78\ud83c\udffd\n\n\n\ud83d\udca6 then his cummies he will send \ud83d\udca9", "likes": null, "suggested_sort": "confidence", "user_reports": [], "secure_media": null, "saved": false, "id": "5e5nfu", "gilded": 0, "secure_media_embed": {}, "clicked": false, "report_reasons": null, "author": "Nozzlehog", "media": null, "name": "t3_5e5nfu", "score": 31, "approved_by": null, "over_18": false, "removal_reason": null, "hidden": false, "thumbnail": "", "subreddit_id": "t5_39n7p", "edited": false, "link_flair_css_class": null, "author_flair_css_class": null, "downs": 0, "mod_reports": [], "archived": false, "media_embed": {}, "is_self": true, "hide_score": false, "spoiler": false, "permalink": "/r/emojipasta/comments/5e5nfu/when_we_trend/", "locked": false, "stickied": false, "created": 1479782140.0, "url": "https://www.reddit.com/r/emojipasta/comments/5e5nfu/when_we_trend/", "author_flair_text": null, "quarantine": false, "title": "\ud83d\udcaf When we trend \ud83d\udcaf", "created_utc": 1479753340.0, "link_flair_text": null, "distinguished": null, "num_comments": 2, "visited": false, "num_reports": null, "ups": 31}}, {"kind": "t3", "data": {"contest_mode": false, "banned_by": null, "domain": "self.emojipasta", "subreddit": "emojipasta", "selftext_html": "&lt;!-- SC_OFF --&gt;&lt;div class=\"md\"&gt;&lt;p&gt;You \ud83d\ude4ctake\ud83d\udc4b the moon\ud83c\udf19 and you take\ud83d\udc4b the sun\u2600\ufe0f \nYou take everything\ud83d\udd75 that seems like fun\ud83c\udf8a\ud83c\udf89\nYou\ud83d\udc41 stir \u270ait all \ud83c\udf72up and when you&amp;#39;re done,\ud83d\ude4c\ud83d\udd1a\n\ud83c\udf1aRadda\ud83c\udf1a \ud83c\udf1aradda\ud83c\udf1a \ud83c\udf1aradda\ud83c\udf1a \ud83c\udf1ara\ud83c\udf1a \ud83c\udf1aradda\ud83c\udf1a \ud83c\udf1aradda\ud83c\udf1a(you \ud83e\udd17share a big\ud83d\udca6\ud83d\udca6 piece\ud83c\udf70 with everyone\ud83d\udc68\u200d\ud83d\udc69\u200d\ud83d\udc67\u200d\ud83d\udc66)\nSo come\ud83d\udc6f on in, feel\ud83c\udf1e \ud83c\udd93 to do some \ud83d\udc40looking\ud83d\udc40, \ud83d\udea6stay a while cause something&amp;#39;s \ud83d\ude0f\ud83d\ude0falways cooking\ud83c\udf73!\nSo come\ud83d\udc6f on in, feel\ud83c\udf1e \ud83c\udd93 to do some \ud83d\udc40looking\ud83d\udc40, \ud83d\udea6stay a while cause something&amp;#39;s \ud83d\ude0f\ud83d\ude0falways cooking\ud83c\udf73!\nYeah\u203c\ufe0f\nLadies\ud83d\udc69\u200d\u2764\ufe0f\u200d\ud83d\udc8b\u200d\ud83d\udc69 would love\ud83d\ude0d\ud83d\ude0d it\u2705!\nFood\u2049\ufe0f\u2049\ufe0f\ud83c\udf4f\ud83c\udf4e\ud83c\udf50\ud83c\udf4a\ud83c\udf4b\ud83c\udf4c\ud83c\udf49\ud83c\udf47\ud83c\udf53\ud83c\udf48\ud83c\udf52\ud83c\udf51\ud83c\udf4d\ud83c\udf45\ud83c\udf46\ud83c\udf36\ud83c\udf3d\ud83c\udf60\ud83c\udf6f\ud83c\udf5e\ud83e\uddc0\ud83c\udf57\ud83c\udf56\ud83c\udf64\ud83c\udf73\ud83c\udf54\ud83c\udf5f\ud83c\udf2d\ud83c\udf55\ud83c\udf5d\ud83c\udf2e\ud83c\udf2f\ud83c\udf5c\ud83c\udf72\ud83c\udf65\ud83c\udf63\ud83c\udf71\ud83c\udf5b\ud83c\udf59\ud83c\udf5a\ud83c\udf58\ud83c\udf62\ud83c\udf61\ud83c\udf67\ud83c\udf68\ud83c\udf66\ud83c\udf70\ud83c\udf82\ud83c\udf6e\ud83c\udf6c\ud83c\udf6d\ud83c\udf6b\ud83c\udf7f\ud83c\udf69\ud83c\udf6a\ud83c\udf7a\ud83c\udf7b\ud83c\udf77\ud83c\udf78\ud83c\udf79\ud83c\udf7e\ud83c\udf76\ud83c\udf75\u2615\ufe0f\ud83c\udf7c\ud83c\udf74\ud83c\udf7d&lt;/p&gt;\n&lt;/div&gt;&lt;!-- SC_ON --&gt;", "selftext": "You \ud83d\ude4ctake\ud83d\udc4b the moon\ud83c\udf19 and you take\ud83d\udc4b the sun\u2600\ufe0f \nYou take everything\ud83d\udd75 that seems like fun\ud83c\udf8a\ud83c\udf89\nYou\ud83d\udc41 stir \u270ait all \ud83c\udf72up and when you're done,\ud83d\ude4c\ud83d\udd1a\n\ud83c\udf1aRadda\ud83c\udf1a \ud83c\udf1aradda\ud83c\udf1a \ud83c\udf1aradda\ud83c\udf1a \ud83c\udf1ara\ud83c\udf1a \ud83c\udf1aradda\ud83c\udf1a \ud83c\udf1aradda\ud83c\udf1a(you \ud83e\udd17share a big\ud83d\udca6\ud83d\udca6 piece\ud83c\udf70 with everyone\ud83d\udc68\u200d\ud83d\udc69\u200d\ud83d\udc67\u200d\ud83d\udc66)\nSo come\ud83d\udc6f on in, feel\ud83c\udf1e \ud83c\udd93 to do some \ud83d\udc40looking\ud83d\udc40, \ud83d\udea6stay a while cause something's \ud83d\ude0f\ud83d\ude0falways cooking\ud83c\udf73!\nSo come\ud83d\udc6f on in, feel\ud83c\udf1e \ud83c\udd93 to do some \ud83d\udc40looking\ud83d\udc40, \ud83d\udea6stay a while cause something's \ud83d\ude0f\ud83d\ude0falways cooking\ud83c\udf73!\nYeah\u203c\ufe0f\nLadies\ud83d\udc69\u200d\u2764\ufe0f\u200d\ud83d\udc8b\u200d\ud83d\udc69 would love\ud83d\ude0d\ud83d\ude0d it\u2705!\nFood\u2049\ufe0f\u2049\ufe0f\ud83c\udf4f\ud83c\udf4e\ud83c\udf50\ud83c\udf4a\ud83c\udf4b\ud83c\udf4c\ud83c\udf49\ud83c\udf47\ud83c\udf53\ud83c\udf48\ud83c\udf52\ud83c\udf51\ud83c\udf4d\ud83c\udf45\ud83c\udf46\ud83c\udf36\ud83c\udf3d\ud83c\udf60\ud83c\udf6f\ud83c\udf5e\ud83e\uddc0\ud83c\udf57\ud83c\udf56\ud83c\udf64\ud83c\udf73\ud83c\udf54\ud83c\udf5f\ud83c\udf2d\ud83c\udf55\ud83c\udf5d\ud83c\udf2e\ud83c\udf2f\ud83c\udf5c\ud83c\udf72\ud83c\udf65\ud83c\udf63\ud83c\udf71\ud83c\udf5b\ud83c\udf59\ud83c\udf5a\ud83c\udf58\ud83c\udf62\ud83c\udf61\ud83c\udf67\ud83c\udf68\ud83c\udf66\ud83c\udf70\ud83c\udf82\ud83c\udf6e\ud83c\udf6c\ud83c\udf6d\ud83c\udf6b\ud83c\udf7f\ud83c\udf69\ud83c\udf6a\ud83c\udf7a\ud83c\udf7b\ud83c\udf77\ud83c\udf78\ud83c\udf79\ud83c\udf7e\ud83c\udf76\ud83c\udf75\u2615\ufe0f\ud83c\udf7c\ud83c\udf74\ud83c\udf7d", "likes": null, "suggested_sort": "confidence", "user_reports": [], "secure_media": null, "saved": false, "id": "5dzxbs", "gilded": 0, "secure_media_embed": {}, "clicked": false, "report_reasons": null, "author": "Bobularsponge", "media": null, "name": "t3_5dzxbs", "score": 34, "approved_by": null, "over_18": false, "removal_reason": null, "hidden": false, "thumbnail": "", "subreddit_id": "t5_39n7p", "edited": false, "link_flair_css_class": null, "author_flair_css_class": null, "downs": 0, "mod_reports": [], "archived": false, "media_embed": {}, "is_self": true, "hide_score": false, "spoiler": false, "permalink": "/r/emojipasta/comments/5dzxbs/chowder_theme_song/", "locked": false, "stickied": false, "created": 1479702239.0, "url": "https://www.reddit.com/r/emojipasta/comments/5dzxbs/chowder_theme_song/", "author_flair_text": null, "quarantine": false, "title": "Chowder theme song", "created_utc": 1479673439.0, "link_flair_text": null, "distinguished": null, "num_comments": 1, "visited": false, "num_reports": null, "ups": 34}}, {"kind": "t3", "data": {"contest_mode": false, "banned_by": null, "domain": "self.emojipasta", "subreddit": "emojipasta", "selftext_html": null, "selftext": "", "likes": null, "suggested_sort": "confidence", "user_reports": [], "secure_media": null, "saved": false, "id": "5ac1qf", "gilded": 0, "secure_media_embed": {}, "clicked": false, "report_reasons": null, "author": "Jabbol", "media": null, "name": "t3_5ac1qf", "score": 35, "approved_by": null, "over_18": false, "removal_reason": null, "hidden": false, "thumbnail": "", "subreddit_id": "t5_39n7p", "edited": false, "link_flair_css_class": null, "author_flair_css_class": null, "downs": 0, "mod_reports": [], "archived": false, "media_embed": {}, "is_self": true, "hide_score": false, "spoiler": false, "permalink": "/r/emojipasta/comments/5ac1qf/hey_you_grill_comeee_here_and_lick_my_bnnana_like/", "locked": false, "stickied": false, "created": 1477947257.0, "url": "https://www.reddit.com/r/emojipasta/comments/5ac1qf/hey_you_grill_comeee_here_and_lick_my_bnnana_like/", "author_flair_text": null, "quarantine": false, "title": "Hey \ud83d\ude4b you grill \ud83d\udc67\ud83d\udc67 comeee here \ud83d\udc63\ud83d\udc63 and lick \ud83d\ude1d\ud83d\ude1d my bnnana \ud83c\udf4c\ud83c\udf4c like a doggo \ud83d\udc36\ud83d\udc36 lick \ud83d\ude1d his tomatos \ud83c\udf45\ud83c\udf45\ud83c\udf45.", "created_utc": 1477918457.0, "link_flair_text": null, "distinguished": null, "num_comments": 4, "visited": false, "num_reports": null, "ups": 35}}, {"kind": "t3", "data": {"contest_mode": false, "banned_by": null, "domain": "self.emojipasta", "subreddit": "emojipasta", "selftext_html": "&lt;!-- SC_OFF --&gt;&lt;div class=\"md\"&gt;&lt;p&gt;Here&amp;#39;s the church \ud83d\udc92\ud83d\udc92\nHere&amp;#39;s the steeple \ud83d\uddfc\ud83d\uddfc\ud83d\uddfc\nLook inside\ud83d\udeaa\ud83d\udeaa\nFor my massive \ud83d\ude32fuckin cock \ud83c\udf46\ud83c\udf3d\ud83c\udf4cshawty \ud83d\ude02\ud83d\ude02\ud83d\ude02\ud83d\ude02 dank ass \ud83c\udf51 dick af \ud83d\ude02\ud83d\udd92\ud83d\ude02\ud83d\udc4c get it in \ud83d\udd19\ud83d\udd1a\u21a9&lt;/p&gt;\n&lt;/div&gt;&lt;!-- SC_ON --&gt;", "selftext": "Here's the church \ud83d\udc92\ud83d\udc92\nHere's the steeple \ud83d\uddfc\ud83d\uddfc\ud83d\uddfc\nLook inside\ud83d\udeaa\ud83d\udeaa\nFor my massive \ud83d\ude32fuckin cock \ud83c\udf46\ud83c\udf3d\ud83c\udf4cshawty \ud83d\ude02\ud83d\ude02\ud83d\ude02\ud83d\ude02 dank ass \ud83c\udf51 dick af \ud83d\ude02\ud83d\udd92\ud83d\ude02\ud83d\udc4c get it in \ud83d\udd19\ud83d\udd1a\u21a9\n", "likes": null, "suggested_sort": "confidence", "user_reports": [], "secure_media": null, "saved": false, "id": "57zz5s", "gilded": 0, "secure_media_embed": {}, "clicked": false, "report_reasons": null, "author": "Colonel_Angus1", "media": null, "name": "t3_57zz5s", "score": 35, "approved_by": null, "over_18": false, "removal_reason": null, "hidden": false, "thumbnail": "", "subreddit_id": "t5_39n7p", "edited": false, "link_flair_css_class": null, "author_flair_css_class": null, "downs": 0, "mod_reports": [], "archived": false, "media_embed": {}, "is_self": true, "hide_score": false, "spoiler": false, "permalink": "/r/emojipasta/comments/57zz5s/heres_the_church_heres_the_steeple/", "locked": false, "stickied": false, "created": 1476768603.0, "url": "https://www.reddit.com/r/emojipasta/comments/57zz5s/heres_the_church_heres_the_steeple/", "author_flair_text": null, "quarantine": false, "title": "Here's the church \ud83d\udc92 here's the steeple\u2b06\ud83d\udd1d", "created_utc": 1476739803.0, "link_flair_text": null, "distinguished": null, "num_comments": 2, "visited": false, "num_reports": null, "ups": 35}}, {"kind": "t3", "data": {"contest_mode": false, "banned_by": null, "domain": "self.emojipasta", "subreddit": "emojipasta", "selftext_html": "&lt;!-- SC_OFF --&gt;&lt;div class=\"md\"&gt;&lt;p&gt;\ud83d\ude25\ud83d\ude25\ud83d\ude25Vladimir Putin? You mean \ud83d\ude1d DADDYMIR PUTIN \ud83d\ude2b\ud83d\ude25\ud83d\udca6\ud83d\udca6 he&amp;#39;s gonna invade my \ud83e\udd10 privates \ud83d\ude25\ud83d\ude2d\ud83d\ude2d with his \ud83d\udca6\ud83d\udca6\ud83d\udca6CUMMIES\ud83d\udca6\ud83d\udca6\ud83d\udca6 \ud83d\ude2d\ud83d\ude2d Putin? More like Putin my ass \ud83e\udd10\ud83e\udd10\ud83e\udd10\ud83e\udd11\ud83d\ude32\ud83d\udca6\ud83d\udca6 because he&amp;#39;s gonna explode \ud83d\udca6\ud83d\udca6cummies\ud83d\udca6 and destroy \ud83d\ude28 my ass\ud83d\ude2d\ud83d\ude2d\ud83d\ude27\ud83d\ude27&lt;/p&gt;\n&lt;/div&gt;&lt;!-- SC_ON --&gt;", "selftext": "\ud83d\ude25\ud83d\ude25\ud83d\ude25Vladimir Putin? You mean \ud83d\ude1d DADDYMIR PUTIN \ud83d\ude2b\ud83d\ude25\ud83d\udca6\ud83d\udca6 he's gonna invade my \ud83e\udd10 privates \ud83d\ude25\ud83d\ude2d\ud83d\ude2d with his \ud83d\udca6\ud83d\udca6\ud83d\udca6CUMMIES\ud83d\udca6\ud83d\udca6\ud83d\udca6 \ud83d\ude2d\ud83d\ude2d Putin? More like Putin my ass \ud83e\udd10\ud83e\udd10\ud83e\udd10\ud83e\udd11\ud83d\ude32\ud83d\udca6\ud83d\udca6 because he's gonna explode \ud83d\udca6\ud83d\udca6cummies\ud83d\udca6 and destroy \ud83d\ude28 my ass\ud83d\ude2d\ud83d\ude2d\ud83d\ude27\ud83d\ude27", "likes": null, "suggested_sort": "confidence", "user_reports": [], "secure_media": null, "saved": false, "id": "51zpl9", "gilded": 0, "secure_media_embed": {}, "clicked": false, "report_reasons": null, "author": "PicklesMcPopcorn", "media": null, "name": "t3_51zpl9", "score": 35, "approved_by": null, "over_18": false, "removal_reason": null, "hidden": false, "thumbnail": "", "subreddit_id": "t5_39n7p", "edited": false, "link_flair_css_class": null, "author_flair_css_class": null, "downs": 0, "mod_reports": [], "archived": false, "media_embed": {}, "is_self": true, "hide_score": false, "spoiler": false, "permalink": "/r/emojipasta/comments/51zpl9/oc_vladimir_putin_you_mean_daddymir_putin/", "locked": false, "stickied": false, "created": 1473484296.0, "url": "https://www.reddit.com/r/emojipasta/comments/51zpl9/oc_vladimir_putin_you_mean_daddymir_putin/", "author_flair_text": null, "quarantine": false, "title": "[OC] \ud83d\ude25\ud83d\ude25\ud83d\ude25Vladimir Putin? You mean \ud83d\ude1d DADDYMIR PUTIN \ud83d\ude2b\ud83d\ude25\ud83d\udca6\ud83d\udca6", "created_utc": 1473455496.0, "link_flair_text": null, "distinguished": null, "num_comments": 2, "visited": false, "num_reports": null, "ups": 35}}, {"kind": "t3", "data": {"contest_mode": false, "banned_by": null, "domain": "self.emojipasta", "subreddit": "emojipasta", "selftext_html": null, "selftext": "", "likes": null, "suggested_sort": "confidence", "user_reports": [], "secure_media": null, "saved": false, "id": "50l0ej", "gilded": 0, "secure_media_embed": {}, "clicked": false, "report_reasons": null, "author": "Senor_Suenos", "media": null, "name": "t3_50l0ej", "score": 31, "approved_by": null, "over_18": false, "removal_reason": null, "hidden": false, "thumbnail": "", "subreddit_id": "t5_39n7p", "edited": false, "link_flair_css_class": null, "author_flair_css_class": "sad", "downs": 0, "mod_reports": [], "archived": false, "media_embed": {}, "is_self": true, "hide_score": false, "spoiler": false, "permalink": "/r/emojipasta/comments/50l0ej/if_my_girl_and_my_mcchicken_both_drowning_and_i/", "locked": false, "stickied": false, "created": 1472725914.0, "url": "https://www.reddit.com/r/emojipasta/comments/50l0ej/if_my_girl_and_my_mcchicken_both_drowning_and_i/", "author_flair_text": "", "quarantine": false, "title": "If my girl \ud83d\ude1a\ud83d\ude0d\ud83d\ude1c and my McChicken\ud83d\ude0f\ud83d\udc95\ud83d\udc14 both drowning\ud83c\udf0a\ud83d\udca6\ud83d\ude35 and I can only save one \ud83d\ude24\ud83d\ude2d\ud83d\ude1ecatch me at my girls funeral \ud83d\udc23\ud83d\udc95\ud83d\ude0f\ud83d\ude35 with my dick\ud83d\ude35\ud83d\ude0e\ud83c\udf46 \ud83c\udf54\ud83c\udf5f\ud83c\udf54 in the McChicken\ud83d\ude0e\ud83d\ude0e\ud83d\ude0d", "created_utc": 1472697114.0, "link_flair_text": null, "distinguished": null, "num_comments": 0, "visited": false, "num_reports": null, "ups": 31}}, {"kind": "t3", "data": {"contest_mode": false, "banned_by": null, "domain": "self.emojipasta", "subreddit": "emojipasta", "selftext_html": null, "selftext": "", "likes": null, "suggested_sort": "confidence", "user_reports": [], "secure_media": null, "saved": false, "id": "50hx0g", "gilded": 0, "secure_media_embed": {}, "clicked": false, "report_reasons": null, "author": "KillerKreemstar", "media": null, "name": "t3_50hx0g", "score": 31, "approved_by": null, "over_18": false, "removal_reason": null, "hidden": false, "thumbnail": "", "subreddit_id": "t5_39n7p", "edited": false, "link_flair_css_class": null, "author_flair_css_class": null, "downs": 0, "mod_reports": [], "archived": false, "media_embed": {}, "is_self": true, "hide_score": false, "spoiler": false, "permalink": "/r/emojipasta/comments/50hx0g/if_leafy_and_my_girl_both_drowning_and_i_can_only/", "locked": false, "stickied": false, "created": 1472688085.0, "url": "https://www.reddit.com/r/emojipasta/comments/50hx0g/if_leafy_and_my_girl_both_drowning_and_i_can_only/", "author_flair_text": null, "quarantine": false, "title": "If Leafy \ud83d\ude47\ud83c\udffb\ud83d\udc4c\ud83d\udc0d and my girl \ud83d\ude0d\ud83d\udc78both drowning \ud83d\ude31\ud83c\udf0a and I can only save one \ud83d\ude24\ud83d\udc7c catch me at my girls funeral \ud83d\ude14\ud83c\udf39\ud83d\udcf9 p-p-p-p-p playing that shit \ud83d\udd95\u25b6\ufe0f\ud83d\ude0e", "created_utc": 1472659285.0, "link_flair_text": null, "distinguished": null, "num_comments": 0, "visited": false, "num_reports": null, "ups": 31}}, {"kind": "t3", "data": {"contest_mode": false, "banned_by": null, "domain": "self.emojipasta", "subreddit": "emojipasta", "selftext_html": "&lt;!-- SC_OFF --&gt;&lt;div class=\"md\"&gt;&lt;p&gt;I&amp;#39;m the \ud83d\udcaaFitnessGram\u2122\ud83d\udcaa\ud83d\ude02 Pacer\u23f1 Test\ud83d\udcc4 and this is my multistage\ud83d\udcca\ud83d\udc48 aerobic\ud83d\udcaa capacity\ud83d\udde3\ud83d\udca8 test. I work\ud83d\udc77 here everyday\ud83d\udcc5 with my running\ud83c\udfc3 speed\ud83d\ude02\u23f2\ud83d\udea8 and my son\ud83d\udc76\ud83d\ude4c, single lap\ud83d\udd02. Everything in here has a [b\u1d49\u1d49p\ud83d\uddb2] and a [d\u1da6ng\ud83d\udd14]. 1\ufe0f\u20e3 thing I learned\ud83d\udcd3\ud83d\udcd1\ud83d\ude33 after 2\ufe0f\u20e30\ufe0f\u20e3 meters - you never know\ud83d\udeab\ud83e\udd14 WHAT is gonna \ud83d\udca6cum\ud83d\udca6 through that start line\ud83c\udfc1\ud83d\udc4c\ud83d\ude02\ud83d\udca6.&lt;/p&gt;\n&lt;/div&gt;&lt;!-- SC_ON --&gt;", "selftext": "I'm the \ud83d\udcaaFitnessGram\u2122\ud83d\udcaa\ud83d\ude02 Pacer\u23f1 Test\ud83d\udcc4 and this is my multistage\ud83d\udcca\ud83d\udc48 aerobic\ud83d\udcaa capacity\ud83d\udde3\ud83d\udca8 test. I work\ud83d\udc77 here everyday\ud83d\udcc5 with my running\ud83c\udfc3 speed\ud83d\ude02\u23f2\ud83d\udea8 and my son\ud83d\udc76\ud83d\ude4c, single lap\ud83d\udd02. Everything in here has a [b\u1d49\u1d49p\ud83d\uddb2] and a [d\u1da6ng\ud83d\udd14]. 1\ufe0f\u20e3 thing I learned\ud83d\udcd3\ud83d\udcd1\ud83d\ude33 after 2\ufe0f\u20e30\ufe0f\u20e3 meters - you never know\ud83d\udeab\ud83e\udd14 WHAT is gonna \ud83d\udca6cum\ud83d\udca6 through that start line\ud83c\udfc1\ud83d\udc4c\ud83d\ude02\ud83d\udca6.", "likes": null, "suggested_sort": "confidence", "user_reports": [], "secure_media": null, "saved": false, "id": "4y24kt", "gilded": 0, "secure_media_embed": {}, "clicked": false, "report_reasons": null, "author": "NDRXSMDR", "media": null, "name": "t3_4y24kt", "score": 32, "approved_by": null, "over_18": false, "removal_reason": null, "hidden": false, "thumbnail": "", "subreddit_id": "t5_39n7p", "edited": false, "link_flair_css_class": null, "author_flair_css_class": null, "downs": 0, "mod_reports": [], "archived": false, "media_embed": {}, "is_self": true, "hide_score": false, "spoiler": false, "permalink": "/r/emojipasta/comments/4y24kt/im_the_fitnessgram_pacer_test_and_this_is_my/", "locked": false, "stickied": false, "created": 1471413636.0, "url": "https://www.reddit.com/r/emojipasta/comments/4y24kt/im_the_fitnessgram_pacer_test_and_this_is_my/", "author_flair_text": null, "quarantine": false, "title": "I'm the \ud83d\udcaaFitnessGram\u2122\ud83d\udcaa\ud83d\ude02 Pacer\u23f1 Test\ud83d\udcc4 and this is my multistage\ud83d\udcca\ud83d\udc48 aerobic\ud83d\udcaa capacity\ud83d\udde3\ud83d\udca8 test.", "created_utc": 1471384836.0, "link_flair_text": null, "distinguished": null, "num_comments": 1, "visited": false, "num_reports": null, "ups": 32}}, {"kind": "t3", "data": {"contest_mode": false, "banned_by": null, "domain": "self.emojipasta", "subreddit": "emojipasta", "selftext_html": "&lt;!-- SC_OFF --&gt;&lt;div class=\"md\"&gt;&lt;p&gt;Do u think \ud83d\ude49\ud83d\ude15its ok\ud83d\udeab\u26d4\ud83d\udeab to be racist\ud83d\ude21\ud83d\udc7f like this... Calling me mayo\u2601 and cracker\ud83c\udf5e \ud83d\udd33..????? Or eve n BECKY\ud83d\udc78????!!! What is america\ud83c\uddfa\ud83c\uddf8\ud83c\uddfa\ud83c\uddf8\ud83c\uddfa\ud83c\uddf8 becoming that i am ALLOWED\ud83d\ude45\u274cto be treated like THIS!!!!! This is the true \ud83d\udc4d\ud83d\udcaf\ud83d\udcafinjustice\ud83d\ude22\ud83d\udc4e\ud83d\udc4e\ud83d\udc94\ud83d\udeab!! My parents \ud83d\udc6b\ud83d\udc99\ud83d\udc9cdid NOT \u274c\u274c\ud83d\udeabwork so hard to make a living\ud83c\udfe1 to be able to bring me\ud83d\udc78 \ud83d\udc6aand my birth name into this world \ud83c\udf0e!! only for you to call me BECKY! \ud83d\ude4d\ud83d\udc67\ud83d\udc78That is not\ud83d\udc4e\u274c\u274c\ud83d\ude45 my name!! I am so tired \ud83d\ude23\ud83d\ude23\ud83d\ude16of how racist \u274c\ud83d\ude31\ud83d\udca6\ud83d\ude21people are to me! For being white\u274c\ud83d\udcaf\ud83d\udc7b!! I have a black friend!! And i love \ud83d\udc45\ud83d\ude4c\u2764\ud83d\ude23 sushi \ud83c\udf59\ud83c\udf64 \ud83c\udf63!!! I dont see \ud83d\udc40\ud83d\udc40 \ud83d\udc40 color\u26ab\u26aa\ud83d\udd34\ud83d\udd35 so you \ud83d\udc46\ud83d\udc46 shouldn&amp;#39;t either! If the cyber harassment \ud83d\udcbb\ud83d\udcf1 does NOT\u26d4\ud83d\udeab\u274c STOP\ud83d\ude45\u270b\ud83c\udd98 I WILL call\ud83d\udcde\u260e the police!!!!!\ud83d\udc6e&lt;/p&gt;\n&lt;/div&gt;&lt;!-- SC_ON --&gt;", "selftext": "Do u think \ud83d\ude49\ud83d\ude15its ok\ud83d\udeab\u26d4\ud83d\udeab to be racist\ud83d\ude21\ud83d\udc7f like this... Calling me mayo\u2601 and cracker\ud83c\udf5e \ud83d\udd33..????? Or eve n BECKY\ud83d\udc78????!!! What is america\ud83c\uddfa\ud83c\uddf8\ud83c\uddfa\ud83c\uddf8\ud83c\uddfa\ud83c\uddf8 becoming that i am ALLOWED\ud83d\ude45\u274cto be treated like THIS!!!!! This is the true \ud83d\udc4d\ud83d\udcaf\ud83d\udcafinjustice\ud83d\ude22\ud83d\udc4e\ud83d\udc4e\ud83d\udc94\ud83d\udeab!! My parents \ud83d\udc6b\ud83d\udc99\ud83d\udc9cdid NOT \u274c\u274c\ud83d\udeabwork so hard to make a living\ud83c\udfe1 to be able to bring me\ud83d\udc78 \ud83d\udc6aand my birth name into this world \ud83c\udf0e!! only for you to call me BECKY! \ud83d\ude4d\ud83d\udc67\ud83d\udc78That is not\ud83d\udc4e\u274c\u274c\ud83d\ude45 my name!! I am so tired \ud83d\ude23\ud83d\ude23\ud83d\ude16of how racist \u274c\ud83d\ude31\ud83d\udca6\ud83d\ude21people are to me! For being white\u274c\ud83d\udcaf\ud83d\udc7b!! I have a black friend!! And i love \ud83d\udc45\ud83d\ude4c\u2764\ud83d\ude23 sushi \ud83c\udf59\ud83c\udf64 \ud83c\udf63!!! I dont see \ud83d\udc40\ud83d\udc40 \ud83d\udc40 color\u26ab\u26aa\ud83d\udd34\ud83d\udd35 so you \ud83d\udc46\ud83d\udc46 shouldn't either! If the cyber harassment \ud83d\udcbb\ud83d\udcf1 does NOT\u26d4\ud83d\udeab\u274c STOP\ud83d\ude45\u270b\ud83c\udd98 I WILL call\ud83d\udcde\u260e the police!!!!!\ud83d\udc6e", "likes": null, "suggested_sort": "confidence", "user_reports": [], "secure_media": null, "saved": false, "id": "4sbakh", "gilded": 0, "secure_media_embed": {}, "clicked": false, "report_reasons": null, "author": "SpookyStirnerite", "media": null, "name": "t3_4sbakh", "score": 34, "approved_by": null, "over_18": false, "removal_reason": null, "hidden": false, "thumbnail": "", "subreddit_id": "t5_39n7p", "edited": false, "link_flair_css_class": null, "author_flair_css_class": null, "downs": 0, "mod_reports": [], "archived": false, "media_embed": {}, "is_self": true, "hide_score": false, "spoiler": false, "permalink": "/r/emojipasta/comments/4sbakh/do_u_think_its_ok_to_be_racist_like_this_calling/", "locked": false, "stickied": false, "created": 1468277664.0, "url": "https://www.reddit.com/r/emojipasta/comments/4sbakh/do_u_think_its_ok_to_be_racist_like_this_calling/", "author_flair_text": null, "quarantine": false, "title": "Do u think \ud83d\ude49\ud83d\ude15its ok\ud83d\udeab\u26d4\ud83d\udeab to be racist\ud83d\ude21\ud83d\udc7f like this... Calling me mayo\u2601 and cracker\ud83c\udf5e \ud83d\udd33..????? Or eve n BECKY\ud83d\udc78????!!!", "created_utc": 1468248864.0, "link_flair_text": null, "distinguished": null, "num_comments": 10, "visited": false, "num_reports": null, "ups": 34}}, {"kind": "t3", "data": {"contest_mode": false, "banned_by": null, "domain": "self.emojipasta", "subreddit": "emojipasta", "selftext_html": "&lt;!-- SC_OFF --&gt;&lt;div class=\"md\"&gt;&lt;p&gt;Toned\ud83c\udfcb, tan\ud83d\udd76, fit\ud83d\udcaa and ready\ud83d\udc4d\nTurn\ud83d\udd03 it \ud83c\udd99 cause it&amp;#39;s getting heavy\ud83d\udce2\nWild\ud83d\ude4a, wild\ud83d\ude48, West Coast\ud83d\ude49\nThese are the \ud83d\udc6fgirls\ud83d\udc6f I love the most\ud83d\ude0c\nI mean the ones\ud83d\udc49\ud83d\ude4eI mean like she&amp;#39;s the one\ud83d\udc91\nKiss her\ud83d\udc44, touch her\u270a, \ud83d\udca2SQUEEZE\ud83d\udca2her buns\ud83c\udf51&lt;/p&gt;\n\n&lt;p&gt;(Uh!\ud83d\ude24) &lt;/p&gt;\n\n&lt;p&gt;The girl&amp;#39;s a freak\ud83d\ude33\nShe \ud83d\udc4adrive\ud83d\udc4a a Jeep\ud83d\ude9c and live on the beach\ud83c\udfc4\nI&amp;#39;m okay\ud83d\udc4c, I won&amp;#39;t play\ud83d\udc81\nI love the \ud83d\ude09Bay\ud83d\ude09 just like I love L.A\ud83c\udf7e\nVenice Beach \ud83d\udc1aand Palm Springs\ud83c\udf34\ud83d\udca6\n\u2600\ufe0fSummertime is everything\u2600\ufe0f\n\ud83d\ude0eHomeboys\ud83d\ude0e banging out\u270a\ud83d\udca6\n\ud83d\ude29All that ass\ud83c\udf51 HANGING out\ud83d\ude29\n\ud83d\udc59Bikinis\ud83d\udc59, \ud83c\udf46zucchinis\ud83c\udf46,\ud83c\udf78martinis\ud83c\udf78, NO weenies\ud83d\ude45\ud83c\udffc\u274c\ud83c\udf2d\nJust the king\ud83d\udc74\ud83c\udf44 and a queenie\ud83d\udc78\ud83c\udf69&lt;/p&gt;\n\n&lt;p&gt;Katy my lady?\ud83d\ude0f&lt;/p&gt;\n\n&lt;p&gt;(Yeah?\ud83e\udd14)&lt;/p&gt;\n\n&lt;p&gt;LOOKIE\ud83d\udc40 here, baby\ud83d\udc76&lt;/p&gt;\n\n&lt;p&gt;(Uh-huh!\ud83d\ude01)&lt;/p&gt;\n\n&lt;p&gt;I&amp;#39;m all up on ya\ud83d\ude1c\ud83d\udc4c\ud83d\udc48Cause you representing California\ud83d\ude18\ud83c\udf36&lt;/p&gt;\n&lt;/div&gt;&lt;!-- SC_ON --&gt;", "selftext": "Toned\ud83c\udfcb, tan\ud83d\udd76, fit\ud83d\udcaa and ready\ud83d\udc4d\nTurn\ud83d\udd03 it \ud83c\udd99 cause it's getting heavy\ud83d\udce2\nWild\ud83d\ude4a, wild\ud83d\ude48, West Coast\ud83d\ude49\nThese are the \ud83d\udc6fgirls\ud83d\udc6f I love the most\ud83d\ude0c\nI mean the ones\ud83d\udc49\ud83d\ude4eI mean like she's the one\ud83d\udc91\nKiss her\ud83d\udc44, touch her\u270a, \ud83d\udca2SQUEEZE\ud83d\udca2her buns\ud83c\udf51\n\n(Uh!\ud83d\ude24) \n\nThe girl's a freak\ud83d\ude33\nShe \ud83d\udc4adrive\ud83d\udc4a a Jeep\ud83d\ude9c and live on the beach\ud83c\udfc4\nI'm okay\ud83d\udc4c, I won't play\ud83d\udc81\nI love the \ud83d\ude09Bay\ud83d\ude09 just like I love L.A\ud83c\udf7e\nVenice Beach \ud83d\udc1aand Palm Springs\ud83c\udf34\ud83d\udca6\n\u2600\ufe0fSummertime is everything\u2600\ufe0f\n\ud83d\ude0eHomeboys\ud83d\ude0e banging out\u270a\ud83d\udca6\n\ud83d\ude29All that ass\ud83c\udf51 HANGING out\ud83d\ude29\n\ud83d\udc59Bikinis\ud83d\udc59, \ud83c\udf46zucchinis\ud83c\udf46,\ud83c\udf78martinis\ud83c\udf78, NO weenies\ud83d\ude45\ud83c\udffc\u274c\ud83c\udf2d\nJust the king\ud83d\udc74\ud83c\udf44 and a queenie\ud83d\udc78\ud83c\udf69\n\nKaty my lady?\ud83d\ude0f\n\n(Yeah?\ud83e\udd14)\n\nLOOKIE\ud83d\udc40 here, baby\ud83d\udc76\n \n(Uh-huh!\ud83d\ude01)\n\nI'm all up on ya\ud83d\ude1c\ud83d\udc4c\ud83d\udc48Cause you representing California\ud83d\ude18\ud83c\udf36", "likes": null, "suggested_sort": "confidence", "user_reports": [], "secure_media": null, "saved": false, "id": "4s3018", "gilded": 0, "secure_media_embed": {}, "clicked": false, "report_reasons": null, "author": "CosmicCruiser", "media": null, "name": "t3_4s3018", "score": 29, "approved_by": null, "over_18": false, "removal_reason": null, "hidden": false, "thumbnail": "", "subreddit_id": "t5_39n7p", "edited": false, "link_flair_css_class": null, "author_flair_css_class": null, "downs": 0, "mod_reports": [], "archived": false, "media_embed": {}, "is_self": true, "hide_score": false, "spoiler": false, "permalink": "/r/emojipasta/comments/4s3018/california_girls/", "locked": false, "stickied": false, "created": 1468137504.0, "url": "https://www.reddit.com/r/emojipasta/comments/4s3018/california_girls/", "author_flair_text": null, "quarantine": false, "title": "\ud83d\ude1c California \ud83d\udc59Girls\ud83d\udc59 \ud83c\udf36", "created_utc": 1468108704.0, "link_flair_text": null, "distinguished": null, "num_comments": 4, "visited": false, "num_reports": null, "ups": 29}}, {"kind": "t3", "data": {"contest_mode": false, "banned_by": null, "domain": "self.emojipasta", "subreddit": "emojipasta", "selftext_html": "&lt;!-- SC_OFF --&gt;&lt;div class=\"md\"&gt;&lt;p&gt;HAPPY FOURTH JULY TO MY GEORGE WASHINGSLUTS!!! \ud83c\uddfa\ud83c\uddf8\ud83d\ude29\ud83d\udca6 2\ufe0f\u20e34\ufe0f\u20e30\ufe0f\u20e3 YEARS AGO OUR FOUNDING DADDIES\ud83d\udc74\ud83c\udffb\ud83d\udc74\ud83c\udffb DECLARED THE UNITED SLUTS OF AMERICA BECUM\ud83d\udca6 \ud83d\udc45INDEPENDENT!\ud83c\uddfa\ud83c\uddf8\ud83c\udf89 IN 1\ufe0f\u20e37\ufe0f\u20e37\ufe0f\u20e36\ufe0f\u20e3 AMERICA WAS KNOWN AS LAND OF THE FREE \ud83e\udd18\ud83c\udfff ,HOME OF THE HOES\ud83d\udc85\ud83c\udfff\ud83d\udc85\ud83c\udfff\ud83d\udc85\ud83c\udfff. NOW WE PLEDGE ALLEGIANCE TO THE FLAG\ud83c\uddfa\ud83c\uddf8 TO SHAKE DAT ASS. \ud83c\udf51\ud83d\udca6 \ud83d\ude4c\ud83c\udffdDONT LET YOUR DADDIES DOWN\u270b\ud83c\udfff, TODAY ISNT \ud83d\udeab JUST ABOUT POPPING \ud83c\udf89FIRECRACKERS\ud83c\udf89 BUT ALSO POPPIN DIS \ud83d\udc31PUSSY\ud83d\udc31 \ud83d\ude4aSEND THIS 2\ufe0f\u20e3 ALL OF YOUR FELLOW SLUTS FOR FREEDOM\ud83c\uddfa\ud83c\uddf8\ud83d\udca6GET 2\ufe0f\u20e3 BACK AND YOU\u2019LL BE CUMMING JUST LIKE THE BRITISH DID\ud83d\ude29\ud83d\ude45\ud83c\udfff\ud83d\udca6GET 4\ufe0f\u20e3 BACK AND YOULL BE GETTING SOME JOHN hanCOCK TONITE \ud83d\udc45\ud83d\udca6\ud83d\udc4c\ud83c\udfff\ud83c\udf46 GET 6\ufe0f\u20e3 BACK AND YOU\u2019LL BE A BRAND NEW HOMEMBER OF THE U\ud83d\udc99S\u2764\ufe0fA\ud83c\uddfa\ud83c\uddf8\ud83c\uddfa\ud83c\uddf8 (UNITEDSLUTSOFAMERICA)\ud83d\udc4c\ud83c\udfff\ud83d\ude08&lt;/p&gt;\n&lt;/div&gt;&lt;!-- SC_ON --&gt;", "selftext": " HAPPY FOURTH JULY TO MY GEORGE WASHINGSLUTS!!! \ud83c\uddfa\ud83c\uddf8\ud83d\ude29\ud83d\udca6 2\ufe0f\u20e34\ufe0f\u20e30\ufe0f\u20e3 YEARS AGO OUR FOUNDING DADDIES\ud83d\udc74\ud83c\udffb\ud83d\udc74\ud83c\udffb DECLARED THE UNITED SLUTS OF AMERICA BECUM\ud83d\udca6 \ud83d\udc45INDEPENDENT!\ud83c\uddfa\ud83c\uddf8\ud83c\udf89 IN 1\ufe0f\u20e37\ufe0f\u20e37\ufe0f\u20e36\ufe0f\u20e3 AMERICA WAS KNOWN AS LAND OF THE FREE \ud83e\udd18\ud83c\udfff ,HOME OF THE HOES\ud83d\udc85\ud83c\udfff\ud83d\udc85\ud83c\udfff\ud83d\udc85\ud83c\udfff. NOW WE PLEDGE ALLEGIANCE TO THE FLAG\ud83c\uddfa\ud83c\uddf8 TO SHAKE DAT ASS. \ud83c\udf51\ud83d\udca6 \ud83d\ude4c\ud83c\udffdDONT LET YOUR DADDIES DOWN\u270b\ud83c\udfff, TODAY ISNT \ud83d\udeab JUST ABOUT POPPING \ud83c\udf89FIRECRACKERS\ud83c\udf89 BUT ALSO POPPIN DIS \ud83d\udc31PUSSY\ud83d\udc31 \ud83d\ude4aSEND THIS 2\ufe0f\u20e3 ALL OF YOUR FELLOW SLUTS FOR FREEDOM\ud83c\uddfa\ud83c\uddf8\ud83d\udca6GET 2\ufe0f\u20e3 BACK AND YOU\u2019LL BE CUMMING JUST LIKE THE BRITISH DID\ud83d\ude29\ud83d\ude45\ud83c\udfff\ud83d\udca6GET 4\ufe0f\u20e3 BACK AND YOULL BE GETTING SOME JOHN hanCOCK TONITE \ud83d\udc45\ud83d\udca6\ud83d\udc4c\ud83c\udfff\ud83c\udf46 GET 6\ufe0f\u20e3 BACK AND YOU\u2019LL BE A BRAND NEW HOMEMBER OF THE U\ud83d\udc99S\u2764\ufe0fA\ud83c\uddfa\ud83c\uddf8\ud83c\uddfa\ud83c\uddf8 (UNITEDSLUTSOFAMERICA)\ud83d\udc4c\ud83c\udfff\ud83d\ude08", "likes": null, "suggested_sort": "confidence", "user_reports": [], "secure_media": null, "saved": false, "id": "4raaei", "gilded": 0, "secure_media_embed": {}, "clicked": false, "report_reasons": null, "author": "Tomb_Stoned", "media": null, "name": "t3_4raaei", "score": 32, "approved_by": null, "over_18": false, "removal_reason": null, "hidden": false, "thumbnail": "", "subreddit_id": "t5_39n7p", "edited": false, "link_flair_css_class": null, "author_flair_css_class": "new", "downs": 0, "mod_reports": [], "archived": false, "media_embed": {}, "is_self": true, "hide_score": false, "spoiler": false, "permalink": "/r/emojipasta/comments/4raaei/happy_fourth_july_to_my_george_washingsluts_240/", "locked": false, "stickied": false, "created": 1467710466.0, "url": "https://www.reddit.com/r/emojipasta/comments/4raaei/happy_fourth_july_to_my_george_washingsluts_240/", "author_flair_text": "Noob", "quarantine": false, "title": "HAPPY FOURTH JULY TO MY GEORGE WASHINGSLUTS!!! \ud83c\uddfa\ud83c\uddf8\ud83d\ude29\ud83d\udca6 2\ufe0f\u20e34\ufe0f\u20e30\ufe0f\u20e3 YEARS AGO", "created_utc": 1467681666.0, "link_flair_text": null, "distinguished": null, "num_comments": 1, "visited": false, "num_reports": null, "ups": 32}}, {"kind": "t3", "data": {"contest_mode": false, "banned_by": null, "domain": "self.emojipasta", "subreddit": "emojipasta", "selftext_html": "&lt;!-- SC_OFF --&gt;&lt;div class=\"md\"&gt;&lt;p&gt;\ud83c\udd97 so I usually \ud83d\udeabrefrain\ud83d\udeab from doing this \ud83d\udc4cemoji\ud83d\udc4c shit\ud83d\udca9\ud83d\udca9, but this is \ud83d\udc49so\ud83d\udc48 fucking\ud83d\udc49\ud83d\udc4c imbecilic\u270b that I \ud83d\udeabcould not\ud83d\udeab refuse\ud83d\ude24\ud83d\ude24\ud83c\udd97\ud83c\udd97 so \u2754what\u2754 makes you believe\ud83d\ude07 that \ud83d\udc49you\ud83d\udc48 are somehow\ud83c\udfb2 entitled\ud83d\udc4cto have an opinion\ud83d\udca9\ud83d\udce3 \ud83d\udd1b this topic\u2049\n\ud83d\udcc2\ud83d\udcc2\ud83d\udcc2allow me\u2714to open\ud83c\udd99 my files\ud83d\udcc2\ud83d\udcc2\ud83d\udcc2 one sec,\u270b \u23f3almost done\u23f3\ud83d\udd1c\n\u231b\u231b\u231b\ud83c\udd97 time\u23f0is \ud83c\udd99 and the files\ud83d\udcc2\ud83d\udcc2\ud83d\udcc2 have told \ud83d\udc49me that \ud83d\udca9you\ud83d\udca9 are a fucking\ud83d\udc49\ud83d\udc4c dumbass\ud83d\udca9\ud83c\udf51\ud83d\ude02\ud83d\ude02bro\ud83d\ude02\ud83d\ude02\ud83d\ude02 \ud83c\udfac\ud83c\udfacaand scene.\ud83d\udcc1\ud83d\udcc1\ud83d\udcc1files \ud83d\udc4b\ud83d\udc4bshut\ud83d\udcc1\ud83d\udcc1\ud83d\udcc1&lt;/p&gt;\n&lt;/div&gt;&lt;!-- SC_ON --&gt;", "selftext": "\ud83c\udd97 so I usually \ud83d\udeabrefrain\ud83d\udeab from doing this \ud83d\udc4cemoji\ud83d\udc4c shit\ud83d\udca9\ud83d\udca9, but this is \ud83d\udc49so\ud83d\udc48 fucking\ud83d\udc49\ud83d\udc4c imbecilic\u270b that I \ud83d\udeabcould not\ud83d\udeab refuse\ud83d\ude24\ud83d\ude24\ud83c\udd97\ud83c\udd97 so \u2754what\u2754 makes you believe\ud83d\ude07 that \ud83d\udc49you\ud83d\udc48 are somehow\ud83c\udfb2 entitled\ud83d\udc4cto have an opinion\ud83d\udca9\ud83d\udce3 \ud83d\udd1b this topic\u2049\n\ud83d\udcc2\ud83d\udcc2\ud83d\udcc2allow me\u2714to open\ud83c\udd99 my files\ud83d\udcc2\ud83d\udcc2\ud83d\udcc2 one sec,\u270b \u23f3almost done\u23f3\ud83d\udd1c\n\u231b\u231b\u231b\ud83c\udd97 time\u23f0is \ud83c\udd99 and the files\ud83d\udcc2\ud83d\udcc2\ud83d\udcc2 have told \ud83d\udc49me that \ud83d\udca9you\ud83d\udca9 are a fucking\ud83d\udc49\ud83d\udc4c dumbass\ud83d\udca9\ud83c\udf51\ud83d\ude02\ud83d\ude02bro\ud83d\ude02\ud83d\ude02\ud83d\ude02 \ud83c\udfac\ud83c\udfacaand scene.\ud83d\udcc1\ud83d\udcc1\ud83d\udcc1files \ud83d\udc4b\ud83d\udc4bshut\ud83d\udcc1\ud83d\udcc1\ud83d\udcc1\n", "likes": null, "suggested_sort": "confidence", "user_reports": [], "secure_media": null, "saved": false, "id": "4i831b", "gilded": 0, "secure_media_embed": {}, "clicked": false, "report_reasons": null, "author": "ishitthememes", "media": null, "name": "t3_4i831b", "score": 31, "approved_by": null, "over_18": false, "removal_reason": null, "hidden": false, "thumbnail": "", "subreddit_id": "t5_39n7p", "edited": false, "link_flair_css_class": null, "author_flair_css_class": "new", "downs": 0, "mod_reports": [], "archived": true, "media_embed": {}, "is_self": true, "hide_score": false, "spoiler": false, "permalink": "/r/emojipasta/comments/4i831b/so_i_usually_refrain_from_doing_this_emoji_shit/", "locked": false, "stickied": false, "created": 1462612996.0, "url": "https://www.reddit.com/r/emojipasta/comments/4i831b/so_i_usually_refrain_from_doing_this_emoji_shit/", "author_flair_text": "Noob", "quarantine": false, "title": "\ud83c\udd97 so I usually \ud83d\udeabrefrain\ud83d\udeab from doing this \ud83d\udc4cemoji\ud83d\udc4c shit\ud83d\udca9", "created_utc": 1462584196.0, "link_flair_text": null, "distinguished": null, "num_comments": 2, "visited": false, "num_reports": null, "ups": 31}}, {"kind": "t3", "data": {"contest_mode": false, "banned_by": null, "domain": "self.emojipasta", "subreddit": "emojipasta", "selftext_html": "&lt;!-- SC_OFF --&gt;&lt;div class=\"md\"&gt;&lt;p&gt;Damn \ud83d\ude0f Drake \ud83d\udcaf daddy \ud83d\ude0f\ud83d\udc45 back at it again with \ud83d\udc40 VIEWS \ud83d\udc40. You can \ud83d\udc40 VIEW \ud83d\udca6\ud83d\udc40 this pussy \ud83d\udca6\ud83d\udca6\ud83d\ude48\ud83d\udc45 any day \ud83d\ude0f champagne \ud83d\udca6\ud83d\udc45 daddy \ud83d\ude4f \u2076 6god \ud83d\ude4f more like \ud83d\udca6\ud83d\udc45\ud83d\ude4f SEXgod \ud83d\udd25\ud83d\udca6 cuz you make me \ud83d\udca6WET\ud83d\udca6 \ud83d\ude18 papi \ud83d\ude0d\ud83d\ude0f papiii \ud83d\ude0f\ud83d\udca6 i want to suck \ud83d\udc45\ud83c\udf46\ud83d\ude48\ud83d\udca6 your cock \ud83c\udf46\ud83d\udc45\ud83d\udc14 DRY while \ud83d\ude1c looking \ud83d\udc40 into your \ud83d\ude0f eyes \ud83d\udc40\ud83d\ude49 like an OWL \ud83e\udd89\ud80c\uddb2 my \u2076\ud80c\udd53 OVO \ud83c\udf46 daddy. \ud83d\udc40 VIEWS \ud83d\udc40 from daddies \ud83d\ude0f\ud83d\udca6\ud83d\udc45 COCK \ud83c\udf46\ud83d\udc45\ud83d\udc14\ud83d\udca6&lt;/p&gt;\n&lt;/div&gt;&lt;!-- SC_ON --&gt;", "selftext": "\ufeffDamn \ud83d\ude0f Drake \ud83d\udcaf daddy \ud83d\ude0f\ud83d\udc45 back at it again with \ud83d\udc40 VIEWS \ud83d\udc40. You can \ud83d\udc40 VIEW \ud83d\udca6\ud83d\udc40 this pussy \ud83d\udca6\ud83d\udca6\ud83d\ude48\ud83d\udc45 any day \ud83d\ude0f champagne \ud83d\udca6\ud83d\udc45 daddy \ud83d\ude4f \u2076 6god \ud83d\ude4f more like \ud83d\udca6\ud83d\udc45\ud83d\ude4f SEXgod \ud83d\udd25\ud83d\udca6 cuz you make me \ud83d\udca6WET\ud83d\udca6 \ud83d\ude18 papi \ud83d\ude0d\ud83d\ude0f papiii \ud83d\ude0f\ud83d\udca6 i want to suck \ud83d\udc45\ud83c\udf46\ud83d\ude48\ud83d\udca6 your cock \ud83c\udf46\ud83d\udc45\ud83d\udc14 DRY while \ud83d\ude1c looking \ud83d\udc40 into your \ud83d\ude0f eyes \ud83d\udc40\ud83d\ude49 like an OWL \ud83e\udd89\ud80c\uddb2 my \u2076\ud80c\udd53 OVO \ud83c\udf46 daddy. \ud83d\udc40 VIEWS \ud83d\udc40 from daddies \ud83d\ude0f\ud83d\udca6\ud83d\udc45 COCK \ud83c\udf46\ud83d\udc45\ud83d\udc14\ud83d\udca6", "likes": null, "suggested_sort": "confidence", "user_reports": [], "secure_media": null, "saved": false, "id": "4h9uz7", "gilded": 0, "secure_media_embed": {}, "clicked": false, "report_reasons": null, "author": "iKhuu", "media": null, "name": "t3_4h9uz7", "score": 31, "approved_by": null, "over_18": false, "removal_reason": null, "hidden": false, "thumbnail": "", "subreddit_id": "t5_39n7p", "edited": false, "link_flair_css_class": null, "author_flair_css_class": "", "downs": 0, "mod_reports": [], "archived": true, "media_embed": {}, "is_self": true, "hide_score": false, "spoiler": false, "permalink": "/r/emojipasta/comments/4h9uz7/oc_views_from_daddies_cock/", "locked": false, "stickied": false, "created": 1462149187.0, "url": "https://www.reddit.com/r/emojipasta/comments/4h9uz7/oc_views_from_daddies_cock/", "author_flair_text": "\ud83d\udcaf", "quarantine": false, "title": "[OC] \ud83d\udc40 VIEWS \ud83d\udc40 from daddies \ud83d\ude0f\ud83d\udca6\ud83d\udc45 COCK \ud83c\udf46\ud83d\udc45\ud83d\udc14", "created_utc": 1462120387.0, "link_flair_text": null, "distinguished": null, "num_comments": 1, "visited": false, "num_reports": null, "ups": 31}}, {"kind": "t3", "data": {"contest_mode": false, "banned_by": null, "domain": "self.emojipasta", "subreddit": "emojipasta", "selftext_html": "&lt;!-- SC_OFF --&gt;&lt;div class=\"md\"&gt;&lt;p&gt;It is \u2716not\u2716 \ud83c\udd97right\ud83c\udd97 to \u2694compare\u2696 a \ud83d\ude1c\u270a\ud83c\udf46whore\ud83d\udca6\ud83d\udca6\ud83d\udca6 to a \ud83d\udd2a\ud83d\ude31convict\ud83d\udd2b\ud83d\udca3. A \ud83c\udf46\ud83d\ude1d\ud83c\udf46whore\ud83c\udf46\ud83d\ude1d\ud83c\udf46 is \u274cnot\u274c a \u2708\ud83c\udfe2convict\ud83d\udca3. A \ud83d\udebc\ud83c\udf46\ud83d\udeba\ud83d\udecfwhore\ud83d\udc91 \ud83d\ude32\ud83d\udc4c\ud83c\udffc is just \u2795\u2795another occupation, \u2194like\u2194 \ud83c\udfe4\u2709teacher\ud83d\udcd9\ud83d\ude4b\ud83c\udffb, \ud83c\udfe5\ud83d\udc8adoctor\ud83d\udd2a\ud83d\udc77\ud83c\udffc, \ud83c\udfe2technician\ud83d\udee0\ud83d\udc81\ud83c\udfff, etc. They do \ud83d\udce5serve\ud83d\udce4 the \ud83c\udfe3\ud83c\udfe4society\ud83d\udc92\ud83c\udfdb as well, but\u2757 in a \u27a1different\u27a1 way\ud83d\ude09\ud83d\ude09\ud83d\ude09\ud83d\ude09\ud83d\ude09\ud83d\ude09\ud83d\ude09.&lt;/p&gt;\n&lt;/div&gt;&lt;!-- SC_ON --&gt;", "selftext": "It is \u2716not\u2716 \ud83c\udd97right\ud83c\udd97 to \u2694compare\u2696 a \ud83d\ude1c\u270a\ud83c\udf46whore\ud83d\udca6\ud83d\udca6\ud83d\udca6 to a \ud83d\udd2a\ud83d\ude31convict\ud83d\udd2b\ud83d\udca3. A \ud83c\udf46\ud83d\ude1d\ud83c\udf46whore\ud83c\udf46\ud83d\ude1d\ud83c\udf46 is \u274cnot\u274c a \u2708\ud83c\udfe2convict\ud83d\udca3. A \ud83d\udebc\ud83c\udf46\ud83d\udeba\ud83d\udecfwhore\ud83d\udc91 \ud83d\ude32\ud83d\udc4c\ud83c\udffc is just \u2795\u2795another occupation, \u2194like\u2194 \ud83c\udfe4\u2709teacher\ud83d\udcd9\ud83d\ude4b\ud83c\udffb, \ud83c\udfe5\ud83d\udc8adoctor\ud83d\udd2a\ud83d\udc77\ud83c\udffc, \ud83c\udfe2technician\ud83d\udee0\ud83d\udc81\ud83c\udfff, etc. They do \ud83d\udce5serve\ud83d\udce4 the \ud83c\udfe3\ud83c\udfe4society\ud83d\udc92\ud83c\udfdb as well, but\u2757 in a \u27a1different\u27a1 way\ud83d\ude09\ud83d\ude09\ud83d\ude09\ud83d\ude09\ud83d\ude09\ud83d\ude09\ud83d\ude09.", "likes": null, "suggested_sort": "confidence", "user_reports": [], "secure_media": null, "saved": false, "id": "4dzhzi", "gilded": 0, "secure_media_embed": {}, "clicked": false, "report_reasons": null, "author": "4ync", "media": null, "name": "t3_4dzhzi", "score": 33, "approved_by": null, "over_18": false, "removal_reason": null, "hidden": false, "thumbnail": "", "subreddit_id": "t5_39n7p", "edited": false, "link_flair_css_class": null, "author_flair_css_class": null, "downs": 0, "mod_reports": [], "archived": true, "media_embed": {}, "is_self": true, "hide_score": false, "spoiler": false, "permalink": "/r/emojipasta/comments/4dzhzi/it_is_not_right_to_compare_a_whore_to_a_convict_a/", "locked": false, "stickied": false, "created": 1460195342.0, "url": "https://www.reddit.com/r/emojipasta/comments/4dzhzi/it_is_not_right_to_compare_a_whore_to_a_convict_a/", "author_flair_text": null, "quarantine": false, "title": "It is \u2716not\u2716 \ud83c\udd97right\ud83c\udd97 to \u2694compare\u2696 a \ud83d\ude1c\u270a\ud83c\udf46whore\ud83d\udca6\ud83d\udca6\ud83d\udca6 to a \ud83d\udd2a\ud83d\ude31convict\ud83d\udd2b\ud83d\udca3. A \ud83c\udf46\ud83d\ude1d\ud83c\udf46whore\ud83c\udf46\ud83d\ude1d\ud83c\udf46 is \u274cnot\u274c a \u2708\ud83c\udfe2convict\ud83d\udca3. A \ud83d\udebc\ud83c\udf46\ud83d\udeba\ud83d\udecfwhore\ud83d\udc91 \ud83d\ude32\ud83d\udc4c\ud83c\udffc is just \u2795\u2795another occupation, \u2194like\u2194 \ud83c\udfe4\u2709teacher\ud83d\udcd9\ud83d\ude4b\ud83c\udffb, \ud83c\udfe5\ud83d\udc8adoctor\ud83d\udd2a\ud83d\udc77\ud83c\udffc, \ud83c\udfe2technician\ud83d\udee0\ud83d\udc81\ud83c\udfff, etc. They do \ud83d\udce5serve\ud83d\udce4 the \ud83c\udfe3\ud83c\udfe4society\ud83d\udc92\ud83c\udfdb as well, but\u2757 in a \u27a1different\u27a1 way\ud83d\ude09\ud83d\ude09\ud83d\ude09\ud83d\ude09\ud83d\ude09\ud83d\ude09\ud83d\ude09.", "created_utc": 1460166542.0, "link_flair_text": null, "distinguished": null, "num_comments": 3, "visited": false, "num_reports": null, "ups": 33}}, {"kind": "t3", "data": {"contest_mode": false, "banned_by": null, "domain": "self.emojipasta", "subreddit": "emojipasta", "selftext_html": null, "selftext": "", "likes": null, "suggested_sort": "confidence", "user_reports": [], "secure_media": null, "saved": false, "id": "40s490", "gilded": 0, "secure_media_embed": {}, "clicked": false, "report_reasons": null, "author": "CoffeeGestalt", "media": null, "name": "t3_40s490", "score": 33, "approved_by": null, "over_18": false, "removal_reason": null, "hidden": false, "thumbnail": "", "subreddit_id": "t5_39n7p", "edited": false, "link_flair_css_class": null, "author_flair_css_class": null, "downs": 0, "mod_reports": [], "archived": true, "media_embed": {}, "is_self": true, "hide_score": false, "spoiler": false, "permalink": "/r/emojipasta/comments/40s490/donald_j_trumpthe_only_man_who_knows_howto/", "locked": false, "stickied": false, "created": 1452722181.0, "url": "https://www.reddit.com/r/emojipasta/comments/40s490/donald_j_trumpthe_only_man_who_knows_howto/", "author_flair_text": null, "quarantine": false, "title": "Donald \ud83d\udcb5\ud83d\udcb5\ud83d\udcb5\ud83d\udcb5\ud83d\udcb0\ud83d\udce2\ud83d\udce2J Trump\u270a\ud83d\udd28the only \ud83d\udc68man who\ud83d\udca1\ud83d\udca1\ud83d\udd14 knows how\ud83d\udcde\u260e\ud83d\udce0to stop\u26d4\ud83d\udcf3\ud83d\udcf3the Chinese \ud83c\ude35\ud83d\udebb\ud83c\udf8f\ud83c\ude1a\ud83c\ude2f\ud83c\udf5c\ud83c\udf5c\ud83c\udf5cfrom \u2702\u2702\ud83d\udcd6\ud83d\udca3\ud83d\udd0eripping \u303d\ud83d\udcb2\ud83d\udcb2\ud83d\udcb2\ud83c\udfe7\u2757off \ud83d\uddfd\ud83d\uddfd\ud83d\uddfd\ud83d\ude80\ud83c\uddfa\ud83c\uddf8 America", "created_utc": 1452693381.0, "link_flair_text": null, "distinguished": null, "num_comments": 2, "visited": false, "num_reports": null, "ups": 33}}, {"kind": "t3", "data": {"contest_mode": false, "banned_by": null, "domain": "self.emojipasta", "subreddit": "emojipasta", "selftext_html": "&lt;!-- SC_OFF --&gt;&lt;div class=\"md\"&gt;&lt;p&gt;cake me the FUCK up \ud83c\udf82\ud83c\udf88\ud83c\udf82\ud83c\udf88\ud83c\udf82\ud83c\udf88\ud83c\udf82\ud83c\udf88\ud83c\udf82\ud83c\udf88 happy birthday hAppy birtHday \ud83c\udf82 thats \ud83c\udf70 some happy\ud83c\udf82\ud83c\udf82 birthday right\ud83c\udf82\ud83c\udf82 there\ud83c\udf82\ud83c\udf82\ud83c\udf82 right\ud83c\udf70 there \ud83c\udf70\ud83c\udf70 if i do \u01bda\u04af so my self \ud83c\udf81 i say so \ud83c\udf81 thats what im talking about right there right there (chorus: \u02b3\u1da6\u1d4d\u02b0\u1d57 \u1d57\u02b0\u1d49\u02b3\u1d49) mMMMM\u13b7\u041c\ud83c\udf81\ud83c\udf82\ud83c\udf82\ud83c\udf82 \u041dO0\u041e\u0b20OOOOO\u041e\u0b20\u0b20Oooo\u1d52\u1d52\u1d52\u1d52\u1d52\u1d52\u1d52\u1d52\u1d52\ud83c\udf82\ud83c\udf82\ud83c\udf82\ud83c\udf82\ud83c\udf81\ud83c\udf82\ud83c\udf88\ud83c\udf88\ud83c\udf88\ud83c\udf82\ud83c\udf82 Happy birthday&lt;/p&gt;\n&lt;/div&gt;&lt;!-- SC_ON --&gt;", "selftext": "cake me the FUCK up \ud83c\udf82\ud83c\udf88\ud83c\udf82\ud83c\udf88\ud83c\udf82\ud83c\udf88\ud83c\udf82\ud83c\udf88\ud83c\udf82\ud83c\udf88 happy birthday hAppy birtHday \ud83c\udf82 thats \ud83c\udf70 some happy\ud83c\udf82\ud83c\udf82 birthday right\ud83c\udf82\ud83c\udf82 there\ud83c\udf82\ud83c\udf82\ud83c\udf82 right\ud83c\udf70 there \ud83c\udf70\ud83c\udf70 if i do \u01bda\u04af so my self \ud83c\udf81 i say so \ud83c\udf81 thats what im talking about right there right there (chorus: \u02b3\u1da6\u1d4d\u02b0\u1d57 \u1d57\u02b0\u1d49\u02b3\u1d49) mMMMM\u13b7\u041c\ud83c\udf81\ud83c\udf82\ud83c\udf82\ud83c\udf82 \u041dO0\u041e\u0b20OOOOO\u041e\u0b20\u0b20Oooo\u1d52\u1d52\u1d52\u1d52\u1d52\u1d52\u1d52\u1d52\u1d52\ud83c\udf82\ud83c\udf82\ud83c\udf82\ud83c\udf82\ud83c\udf81\ud83c\udf82\ud83c\udf88\ud83c\udf88\ud83c\udf88\ud83c\udf82\ud83c\udf82 Happy birthday", "likes": null, "suggested_sort": "confidence", "user_reports": [], "secure_media": null, "saved": false, "id": "3s5cce", "gilded": 0, "secure_media_embed": {}, "clicked": false, "report_reasons": null, "author": "supertoasty", "media": null, "name": "t3_3s5cce", "score": 32, "approved_by": null, "over_18": false, "removal_reason": null, "hidden": false, "thumbnail": "", "subreddit_id": "t5_39n7p", "edited": false, "link_flair_css_class": "", "author_flair_css_class": null, "downs": 0, "mod_reports": [], "archived": true, "media_embed": {}, "is_self": true, "hide_score": false, "spoiler": false, "permalink": "/r/emojipasta/comments/3s5cce/happy_birthday/", "locked": false, "stickied": false, "created": 1447114791.0, "url": "https://www.reddit.com/r/emojipasta/comments/3s5cce/happy_birthday/", "author_flair_text": null, "quarantine": false, "title": "Happy birthday \ud83c\udf82\ud83c\udf88\ud83c\udf82\ud83c\udf88", "created_utc": 1447085991.0, "link_flair_text": "Cakeday", "distinguished": null, "num_comments": 1, "visited": false, "num_reports": null, "ups": 32}}, {"kind": "t3", "data": {"contest_mode": false, "banned_by": null, "domain": "self.emojipasta", "subreddit": "emojipasta", "selftext_html": "&lt;!-- SC_OFF --&gt;&lt;div class=\"md\"&gt;&lt;p&gt;\u2693\ufe0f\ud83d\udc33\u2693\ufe0f\ud83d\udc33\u2693\ufe0f\ud83d\udc33\u2693\ufe0f\ud83d\udc33\u2693\ufe0f\ud83d\udc33navy seal navy sEal \u2693\ufe0f that&amp;#39;s\u26f5\ufe0f a navy \u2693\ufe0f\u2693\ufe0f seal right \u2693\ufe0f\u2693\ufe0f right \u26f5\ufe0f there \ud83d\udea4\ud83d\udea4 if I do \u01bda\u04af so myself \ud83d\udea2 I say so \ud83d\udea2 that&amp;#39;s what I&amp;#39;m talking about right there right there \n(chorus: \u02b3\u1da6\u1d4d\u02b0\u1d57 \u1d57\u02b0\u1d49\u02b3\u1d49) \nmMMMM\u13b7\u041c \u2693\ufe0f\u2693\ufe0f\u2693\u26f5\ufe0f\ufe0f\u041dO0\u041e\u0b20OOOOO\u041e\u0b20\u0b20Oooo\u1d52\u1d52\u1d52\u1d52\u1d52\u1d52\u1d52\u1d52 \u2693\ufe0f\u2693\ufe0f\u2693\ufe0f\u2693\ufe0f\u26f5\ufe0f\u2693\ufe0f\ud83d\udc33\ud83d\udc33\ud83d\udc33\u2693\ufe0f\u2693\ufe0f good shit&lt;/p&gt;\n\n&lt;p&gt;My rendition&lt;/p&gt;\n&lt;/div&gt;&lt;!-- SC_ON --&gt;", "selftext": "\u2693\ufe0f\ud83d\udc33\u2693\ufe0f\ud83d\udc33\u2693\ufe0f\ud83d\udc33\u2693\ufe0f\ud83d\udc33\u2693\ufe0f\ud83d\udc33navy seal navy sEal \u2693\ufe0f that's\u26f5\ufe0f a navy \u2693\ufe0f\u2693\ufe0f seal right \u2693\ufe0f\u2693\ufe0f right \u26f5\ufe0f there \ud83d\udea4\ud83d\udea4 if I do \u01bda\u04af so myself \ud83d\udea2 I say so \ud83d\udea2 that's what I'm talking about right there right there \n(chorus: \u02b3\u1da6\u1d4d\u02b0\u1d57 \u1d57\u02b0\u1d49\u02b3\u1d49) \nmMMMM\u13b7\u041c \u2693\ufe0f\u2693\ufe0f\u2693\u26f5\ufe0f\ufe0f\u041dO0\u041e\u0b20OOOOO\u041e\u0b20\u0b20Oooo\u1d52\u1d52\u1d52\u1d52\u1d52\u1d52\u1d52\u1d52 \u2693\ufe0f\u2693\ufe0f\u2693\ufe0f\u2693\ufe0f\u26f5\ufe0f\u2693\ufe0f\ud83d\udc33\ud83d\udc33\ud83d\udc33\u2693\ufe0f\u2693\ufe0f good shit\n\nMy rendition", "likes": null, "suggested_sort": "confidence", "user_reports": [], "secure_media": null, "saved": false, "id": "3iemfw", "gilded": 0, "secure_media_embed": {}, "clicked": false, "report_reasons": null, "author": "L4PU7A", "media": null, "name": "t3_3iemfw", "score": 32, "approved_by": null, "over_18": false, "removal_reason": null, "hidden": false, "thumbnail": "", "subreddit_id": "t5_39n7p", "edited": false, "link_flair_css_class": null, "author_flair_css_class": null, "downs": 0, "mod_reports": [], "archived": true, "media_embed": {}, "is_self": true, "hide_score": false, "spoiler": false, "permalink": "/r/emojipasta/comments/3iemfw/navy_seal_navy_seal_thats_a_navy_seal_right_right/", "locked": false, "stickied": false, "created": 1440578533.0, "url": "https://www.reddit.com/r/emojipasta/comments/3iemfw/navy_seal_navy_seal_thats_a_navy_seal_right_right/", "author_flair_text": null, "quarantine": false, "title": "\u2693\ufe0f\ud83d\udc33\u2693\ufe0f\ud83d\udc33\u2693\ufe0f\ud83d\udc33\u2693\ufe0f\ud83d\udc33\u2693\ufe0f\ud83d\udc33navy seal navy sEal \u2693\ufe0f that's\u26f5\ufe0f a navy \u2693\ufe0f\u2693\ufe0f seal right \u2693\ufe0f\u2693\ufe0f right \u26f5\ufe0f there \ud83d\udea4\ud83d\udea4 if I do \u01bda\u04af so myself \ud83d\udea2 I say so \ud83d\udea2 that's what I'm talking about right there right there (chorus: \u02b3\u1da6\u1d4d\u02b0\u1d57 \u1d57\u02b0\u1d49\u02b3\u1d49) mMMMM\u13b7\u041c \u2693\ufe0f\u2693\ufe0f\u2693\u26f5\ufe0f\ufe0f\u041dO0\u041e\u0b20OOOOO\u041e\u0b20\u0b20Oooo\u1d52\u1d52\u1d52\u1d52\u1d52\u1d52\u1d52\u1d52 \u2693\ufe0f\u2693\ufe0f\u2693\ufe0f\u2693\ufe0f\u26f5\ufe0f\u2693\ufe0f\ud83d\udc33\ud83d\udc33\ud83d\udc33\u2693\ufe0f\u2693\ufe0f good shit", "created_utc": 1440549733.0, "link_flair_text": null, "distinguished": null, "num_comments": 6, "visited": false, "num_reports": null, "ups": 32}}, {"kind": "t3", "data": {"contest_mode": false, "banned_by": null, "domain": "self.emojipasta", "subreddit": "emojipasta", "selftext_html": "&lt;!-- SC_OFF --&gt;&lt;div class=\"md\"&gt;&lt;p&gt;Do \ud83d\udc49you\ud83d\udc48\ud83d\udd4dbelieve\ud83d\udc7c\ud83d\ude07your s\ud83c\udd7fouse\ud83e\udd35\ud83d\udc70or\u2764lover\ud83c\udf46\ud83d\udca6\ud83d\udca6is cheating\ud83d\udc94\ud83d\ude08on\ud83e\udd14you\ud83d\ude2eand you\ud83d\ude22want them\ud83d\udc6b\ud83d\udc6b t\ud83c\udd7e take\u270da \ud83e\udd25\ud83e\udd25lie\ud83d\ude4adetector\ud83d\udd1ctest??\ud83d\udcc3\u270d CALL\ud83d\udcde\ud83d\udcf1 1-888-45M\ud83c\udd70URY\ud83d\udc74\ud83d\udc74&lt;/p&gt;\n&lt;/div&gt;&lt;!-- SC_ON --&gt;", "selftext": "Do \ud83d\udc49you\ud83d\udc48\ud83d\udd4dbelieve\ud83d\udc7c\ud83d\ude07your s\ud83c\udd7fouse\ud83e\udd35\ud83d\udc70or\u2764lover\ud83c\udf46\ud83d\udca6\ud83d\udca6is cheating\ud83d\udc94\ud83d\ude08on\ud83e\udd14you\ud83d\ude2eand you\ud83d\ude22want them\ud83d\udc6b\ud83d\udc6b t\ud83c\udd7e take\u270da \ud83e\udd25\ud83e\udd25lie\ud83d\ude4adetector\ud83d\udd1ctest??\ud83d\udcc3\u270d CALL\ud83d\udcde\ud83d\udcf1 1-888-45M\ud83c\udd70URY\ud83d\udc74\ud83d\udc74", "likes": null, "suggested_sort": "confidence", "user_reports": [], "secure_media": null, "saved": false, "id": "5h0gax", "gilded": 0, "secure_media_embed": {}, "clicked": false, "report_reasons": null, "author": "bmildenh", "media": null, "name": "t3_5h0gax", "score": 34, "approved_by": null, "over_18": false, "removal_reason": null, "hidden": false, "thumbnail": "", "subreddit_id": "t5_39n7p", "edited": false, "link_flair_css_class": null, "author_flair_css_class": null, "downs": 0, "mod_reports": [], "archived": false, "media_embed": {}, "is_self": true, "hide_score": false, "spoiler": false, "permalink": "/r/emojipasta/comments/5h0gax/call_188845mury/", "locked": false, "stickied": false, "created": 1481153038.0, "url": "https://www.reddit.com/r/emojipasta/comments/5h0gax/call_188845mury/", "author_flair_text": null, "quarantine": false, "title": "CALL\ud83d\udcde\ud83d\udcf1 1-888-45M\ud83c\udd70URY\ud83d\udc74\ud83d\udc74", "created_utc": 1481124238.0, "link_flair_text": null, "distinguished": null, "num_comments": 2, "visited": false, "num_reports": null, "ups": 34}}, {"kind": "t3", "data": {"contest_mode": false, "banned_by": null, "domain": "self.emojipasta", "subreddit": "emojipasta", "selftext_html": "&lt;!-- SC_OFF --&gt;&lt;div class=\"md\"&gt;&lt;p&gt;\ud83c\udf85 If a Fat Man comes into your room in the middle of the night \ud83c\udf03, &amp;amp; shoves you into a Bag, don&amp;#39;t be scared cause I told Santa \ud83c\udf85, I wanted a Friend like YOU for Christmas \ud83c\udf84!!!\nSend this to everyone you care about, including me. If you get it back 4 times, you&amp;#39;re real!!! \n\ud83c\udf85 \ud83c\udf85 \ud83c\udf85 \ud83c\udf85 \ud83c\udf85 \ud83c\udf85 \ud83c\udf85 \ud83c\udf85 \ud83c\udf85 \ud83c\udf85&lt;/p&gt;\n&lt;/div&gt;&lt;!-- SC_ON --&gt;", "selftext": "\ud83c\udf85 If a Fat Man comes into your room in the middle of the night \ud83c\udf03, &amp; shoves you into a Bag, don't be scared cause I told Santa \ud83c\udf85, I wanted a Friend like YOU for Christmas \ud83c\udf84!!!\nSend this to everyone you care about, including me. If you get it back 4 times, you're real!!! \n\ud83c\udf85 \ud83c\udf85 \ud83c\udf85 \ud83c\udf85 \ud83c\udf85 \ud83c\udf85 \ud83c\udf85 \ud83c\udf85 \ud83c\udf85 \ud83c\udf85", "likes": null, "suggested_sort": "confidence", "user_reports": [], "secure_media": null, "saved": false, "id": "5fmpbi", "gilded": 0, "secure_media_embed": {}, "clicked": false, "report_reasons": null, "author": "jaspanye", "media": null, "name": "t3_5fmpbi", "score": 32, "approved_by": null, "over_18": false, "removal_reason": null, "hidden": false, "thumbnail": "", "subreddit_id": "t5_39n7p", "edited": false, "link_flair_css_class": null, "author_flair_css_class": "Ghetto", "downs": 0, "mod_reports": [], "archived": false, "media_embed": {}, "is_self": true, "hide_score": false, "spoiler": false, "permalink": "/r/emojipasta/comments/5fmpbi/i_got_this_from_my_grandmas_messages/", "locked": false, "stickied": false, "created": 1480497907.0, "url": "https://www.reddit.com/r/emojipasta/comments/5fmpbi/i_got_this_from_my_grandmas_messages/", "author_flair_text": "S A D B O Y S", "quarantine": false, "title": "I got this from my grandma's messages", "created_utc": 1480469107.0, "link_flair_text": null, "distinguished": null, "num_comments": 3, "visited": false, "num_reports": null, "ups": 32}}, {"kind": "t3", "data": {"contest_mode": false, "banned_by": null, "domain": "discord.gg", "subreddit": "emojipasta", "selftext_html": null, "selftext": "", "likes": null, "suggested_sort": "confidence", "user_reports": [], "secure_media": null, "saved": false, "id": "5am4p8", "gilded": 0, "secure_media_embed": {}, "clicked": false, "report_reasons": null, "author": "emersonic420", "media": null, "name": "t3_5am4p8", "score": 30, "approved_by": null, "over_18": false, "removal_reason": null, "hidden": false, "thumbnail": "", "subreddit_id": "t5_39n7p", "edited": false, "link_flair_css_class": null, "author_flair_css_class": "mod", "downs": 0, "mod_reports": [], "archived": false, "media_embed": {}, "is_self": false, "hide_score": false, "spoiler": false, "permalink": "/r/emojipasta/comments/5am4p8/cum_make_some_sexy_emoji_pastas_on_our_discord/", "locked": false, "stickied": false, "created": 1478067314.0, "url": "https://discord.gg/FS6MpfH", "author_flair_text": "creator of /r/EmojiPasta", "quarantine": false, "title": "Cum make some \ud83d\ude0d \ud83d\ude18sexy\ud83d\udc45\ud83d\udc45 Emoji Pastas on our Discord server!\ud83d\udc4f\ud83d\udc4f\ud83d\udc4f", "created_utc": 1478038514.0, "link_flair_text": null, "distinguished": "moderator", "num_comments": 3, "visited": false, "num_reports": null, "ups": 30}}, {"kind": "t3", "data": {"contest_mode": false, "banned_by": null, "domain": "self.emojipasta", "subreddit": "emojipasta", "selftext_html": "&lt;!-- SC_OFF --&gt;&lt;div class=\"md\"&gt;&lt;p&gt;I\ud83d\ude00PERSONALLY\ud83d\udc48 FIND IT VERY\ud83c\udf89 FUNNY\ud83d\ude02\ud83d\ude02 TO MAKE \ud83d\udca6\ud83d\udca6\ud83d\udca6CUMMYBOT\ud83d\udca6\ud83d\udca6\ud83d\udca6 SAY \ud83e\udd10AMUSING \ud83d\ude06THINGS SO I\ud83d\ude00 CAN \u26b1\ufe0fREPLY\ud83d\udce4 ACTING\ud83c\udfad LIKE \ud83d\udca6\ud83d\udca6\ud83d\udca6CUMMYBOT\ud83d\udca6\ud83d\udca6\ud83d\udca6 IS AN ACTUAL\ud83d\ude26 HUMAN\ud83d\udc6c\ud83d\udc6d\ud83d\udc6b TO RAISE\u23eb MY KARMA\u2b06\ufe0f\u2b06\ufe0f COUNT1\ufe0f\u20e32\ufe0f\u20e33\ufe0f\u20e34\ufe0f\u20e3. &lt;/p&gt;\n&lt;/div&gt;&lt;!-- SC_ON --&gt;", "selftext": "I\ud83d\ude00PERSONALLY\ud83d\udc48 FIND IT VERY\ud83c\udf89 FUNNY\ud83d\ude02\ud83d\ude02 TO MAKE \ud83d\udca6\ud83d\udca6\ud83d\udca6CUMMYBOT\ud83d\udca6\ud83d\udca6\ud83d\udca6 SAY \ud83e\udd10AMUSING \ud83d\ude06THINGS SO I\ud83d\ude00 CAN \u26b1\ufe0fREPLY\ud83d\udce4 ACTING\ud83c\udfad LIKE \ud83d\udca6\ud83d\udca6\ud83d\udca6CUMMYBOT\ud83d\udca6\ud83d\udca6\ud83d\udca6 IS AN ACTUAL\ud83d\ude26 HUMAN\ud83d\udc6c\ud83d\udc6d\ud83d\udc6b TO RAISE\u23eb MY KARMA\u2b06\ufe0f\u2b06\ufe0f COUNT1\ufe0f\u20e32\ufe0f\u20e33\ufe0f\u20e34\ufe0f\u20e3. ", "likes": null, "suggested_sort": "confidence", "user_reports": [], "secure_media": null, "saved": false, "id": "59ea29", "gilded": 0, "secure_media_embed": {}, "clicked": false, "report_reasons": null, "author": "theapplebrit", "media": null, "name": "t3_59ea29", "score": 32, "approved_by": null, "over_18": false, "removal_reason": null, "hidden": false, "thumbnail": "", "subreddit_id": "t5_39n7p", "edited": false, "link_flair_css_class": null, "author_flair_css_class": "Ghetto", "downs": 0, "mod_reports": [], "archived": false, "media_embed": {}, "is_self": true, "hide_score": false, "spoiler": false, "permalink": "/r/emojipasta/comments/59ea29/cummybot_meta_post/", "locked": false, "stickied": false, "created": 1477466506.0, "url": "https://www.reddit.com/r/emojipasta/comments/59ea29/cummybot_meta_post/", "author_flair_text": "S A D B O Y S", "quarantine": false, "title": "\ud83d\udca6\ud83d\udca6CUMMYBOT \ud83d\udca6\ud83d\udca6META \ud83d\udce5POST\ud83d\udccc", "created_utc": 1477437706.0, "link_flair_text": null, "distinguished": null, "num_comments": 6, "visited": false, "num_reports": null, "ups": 32}}], "after": "t3_59ea29", "before": null}}